{
  "Dlcs": {
    "2028055": {
      "Name": "Tom Clancy's Ghost Recon Future Soldier - Season Pass",
      "ImageUrl": "https://steamcdn-a.akamaihd.net/steam/apps/2028055/header.jpg?t=1447356562"
    },
    "212673": {
      "Name": "Tom Clancy's Ghost Recon Future Soldier® - Khyber Strike",
      "ImageUrl": "https://steamcdn-a.akamaihd.net/steam/apps/212673/header.jpg?t=1447357308"
    },
    "212672": {
      "Name": "Tom Clancy's Ghost Recon Future Soldier® Raven Strike DLC",
      "ImageUrl": "https://steamcdn-a.akamaihd.net/steam/apps/212672/header.jpg?t=1447357064"
    },
    "212671": {
      "Name": "Tom Clancy's Ghost Recon Future Soldier - Arctic Strike DLC",
      "ImageUrl": "https://steamcdn-a.akamaihd.net/steam/apps/212671/header.jpg?t=1447356499"
    }
  },
  "Name": "Tom Clancy's Ghost Recon: Future Soldier™",
  "AppId": "212630",
  "ImageUrl": "https://steamcdn-a.akamaihd.net/steam/apps/212630/header.jpg?t=1472606318",
  "Languages": [
    "english",
    "danish",
    "dutch",
    "french",
    "german",
    "italian",
    "norwegian",
    "polish",
    "portuguese",
    "spanish",
    "swedish"
  ],
  "Platforms": {
    "windows": true,
    "mac": false,
    "linux": false
  }
}