{
  "Dlcs": {
    "1302380": {
      "Name": "Q - Original Game Soundtrack",
      "ImageUrl": "https://cdn.akamai.steamstatic.com/steam/apps/1302380/header.jpg?t=1595191839",
      "Type": "music"
    }
  },
  "Name": "Q - A Neon Platformer",
  "AppId": "1071280",
  "ImageUrl": "https://cdn.akamai.steamstatic.com/steam/apps/1071280/header.jpg?t=1626254689",
  "Languages": [
    "english",
    "german",
    "french",
    "spanish"
  ],
  "Platforms": {
    "windows": true,
    "mac": false,
    "linux": false
  }
}