{
  "Dlcs": {},
  "Name": "SPEED BOX",
  "AppId": "886490",
  "ImageUrl": "https://steamcdn-a.akamaihd.net/steam/apps/886490/header.jpg?t=1558394231",
  "Languages": [
    "english",
    "french",
    "italian",
    "german",
    "spanish",
    "arabic",
    "ukrainian",
    "dutch",
    "greek",
    "swedish",
    "thai",
    "czech",
    "danish",
    "turkish",
    "norwegian",
    "hungarian",
    "finnish",
    "bulgarian",
    "portuguese",
    "polish",
    "romanian",
    "russian",
    "schinese",
    "tchinese",
    "japanese",
    "korean"
  ],
  "Platforms": {
    "windows": true,
    "mac": false,
    "linux": false
  }
}