{
  "Dlcs": {
    "644690": {
      "Name": "UltraGoodness - Soundtrack",
      "ImageUrl": "https://steamcdn-a.akamaihd.net/steam/apps/644690/header.jpg?t=1571426554"
    }
  },
  "Name": "UltraGoodness",
  "AppId": "610130",
  "ImageUrl": "https://steamcdn-a.akamaihd.net/steam/apps/610130/header.jpg?t=1571426482",
  "Languages": [
    "english",
    "french",
    "italian",
    "german",
    "spanish",
    "portuguese",
    "portuguese",
    "russian",
    "japanese",
    "schinese"
  ],
  "Platforms": {
    "windows": true,
    "mac": false,
    "linux": false
  }
}