{
  "Dlcs": {
    "1209470": {
      "Name": "American Truck Simulator - Idaho",
      "ImageUrl": "https://steamcdn-a.akamaihd.net/steam/apps/1209470/header.jpg?t=1594915281"
    },
    "1209471": {
      "Name": "American Truck Simulator - Colorado",
      "ImageUrl": "https://steamcdn-a.akamaihd.net/steam/apps/1209471/header.jpg?t=1596020514"
    },
    "1104880": {
      "Name": "American Truck Simulator - Utah",
      "ImageUrl": "https://steamcdn-a.akamaihd.net/steam/apps/1104880/header.jpg?t=1573150184"
    },
    "1015160": {
      "Name": "American Truck Simulator - Washington",
      "ImageUrl": "https://steamcdn-a.akamaihd.net/steam/apps/1015160/header.jpg?t=1560351581"
    },
    "800370": {
      "Name": "American Truck Simulator - Oregon",
      "ImageUrl": "https://steamcdn-a.akamaihd.net/steam/apps/800370/header.jpg?t=1568813486"
    },
    "684630": {
      "Name": "American Truck Simulator - New Mexico",
      "ImageUrl": "https://steamcdn-a.akamaihd.net/steam/apps/684630/header.jpg?t=1582565193"
    },
    "962750": {
      "Name": "American Truck Simulator - Special Transport",
      "ImageUrl": "https://steamcdn-a.akamaihd.net/steam/apps/962750/header.jpg?t=1580830999"
    },
    "1076080": {
      "Name": "American Truck Simulator - Forest Machinery",
      "ImageUrl": "https://steamcdn-a.akamaihd.net/steam/apps/1076080/header.jpg?t=1581087653"
    },
    "620610": {
      "Name": "American Truck Simulator - Heavy Cargo Pack",
      "ImageUrl": "https://steamcdn-a.akamaihd.net/steam/apps/620610/header.jpg?t=1580922395"
    },
    "450550": {
      "Name": "American Truck Simulator - Wheel Tuning Pack",
      "ImageUrl": "https://steamcdn-a.akamaihd.net/steam/apps/450550/header.jpg?t=1564078676"
    },
    "520550": {
      "Name": "American Truck Simulator - Steering Creations Pack",
      "ImageUrl": "https://steamcdn-a.akamaihd.net/steam/apps/520550/header.jpg?t=1474480602"
    },
    "463740": {
      "Name": "American Truck Simulator - Arizona",
      "ImageUrl": "https://steamcdn-a.akamaihd.net/steam/apps/463740/header.jpg?t=1465220145"
    },
    "561620": {
      "Name": "American Truck Simulator - Dragon Truck Design Pack",
      "ImageUrl": "https://steamcdn-a.akamaihd.net/steam/apps/561620/header.jpg?t=1547247402"
    },
    "1116310": {
      "Name": "American Truck Simulator - Space Paint Jobs Pack",
      "ImageUrl": "https://steamcdn-a.akamaihd.net/steam/apps/1116310/header.jpg?t=1563197550"
    },
    "951650": {
      "Name": "American Truck Simulator - Classic Stripes Paint Jobs Pack",
      "ImageUrl": "https://steamcdn-a.akamaihd.net/steam/apps/951650/header.jpg?t=1538661712"
    },
    "566890": {
      "Name": "American Truck Simulator - Christmas Paint Jobs Pack",
      "ImageUrl": "https://steamcdn-a.akamaihd.net/steam/apps/566890/header.jpg?t=1481881617"
    },
    "588600": {
      "Name": "American Truck Simulator - Valentine's Paint Jobs Pack",
      "ImageUrl": "https://steamcdn-a.akamaihd.net/steam/apps/588600/header.jpg?t=1486719797"
    },
    "546260": {
      "Name": "American Truck Simulator - Halloween Paint Jobs Pack",
      "ImageUrl": "https://steamcdn-a.akamaihd.net/steam/apps/546260/header.jpg?t=1540834875"
    },
    "1162160": {
      "Name": "American Truck Simulator - Pink Ribbon Charity Pack",
      "ImageUrl": "https://steamcdn-a.akamaihd.net/steam/apps/1162160/header.jpg?t=1571661224"
    },
    "1236650": {
      "Name": "American Truck Simulator - Mack Anthem®",
      "ImageUrl": "https://steamcdn-a.akamaihd.net/steam/apps/1236650/header.jpg?t=1588141343"
    },
    "1415691": {
      "Name": "American Truck Simulator - Western Star® 49X",
      "ImageUrl": "https://steamcdn-a.akamaihd.net/steam/apps/1415691/header.jpg?t=1601484494"
    },
    "1415692": {
      "Name": "American Truck Simulator - Wyoming",
      "ImageUrl": "https://cdn.akamai.steamstatic.com/steam/apps/1415692/header.jpg?t=1630087559",
      "Type": "dlc"
    },
    "1415690": {
      "Name": "American Truck Simulator - Freightliner Cascadia®",
      "ImageUrl": "https://cdn.akamai.steamstatic.com/steam/apps/1415690/header.jpg?t=1606929621",
      "Type": "dlc"
    }
  },
  "Name": "American Truck Simulator",
  "AppId": "270880",
  "ImageUrl": "https://steamcdn-a.akamaihd.net/steam/apps/270880/header.jpg?t=1594915013",
  "Languages": [
    "english",
    "french",
    "italian",
    "german",
    "spanish",
    "bulgarian",
    "czech",
    "danish",
    "dutch",
    "finnish",
    "greek",
    "hungarian",
    "japanese",
    "korean",
    "norwegian",
    "polish",
    "portuguese",
    "portuguese",
    "romanian",
    "russian",
    "schinese",
    "swedish",
    "turkish",
    "ukrainian"
  ],
  "Platforms": {
    "windows": true,
    "mac": true,
    "linux": true
  }
}