{
  "Dlcs": {},
  "Name": "Inversion",
  "AppId": "1505430",
  "ImageUrl": "https://cdn.akamai.steamstatic.com/steam/apps/1505430/header.jpg?t=1613638443",
  "Languages": [
    "english",
    "italian",
    "spanish",
    "arabic",
    "portuguese",
    "vietnamese",
    "danish",
    "tchinese",
    "korean",
    "norwegian",
    "portuguese",
    "russian",
    "turkish",
    "finnish",
    "swedish",
    "french",
    "german",
    "bulgarian",
    "hungarian",
    "greek",
    "latam",
    "schinese",
    "dutch",
    "polish",
    "romanian",
    "thai",
    "ukrainian",
    "czech",
    "japanese"
  ],
  "Platforms": {
    "windows": true,
    "mac": false,
    "linux": false
  }
}