{
  "Dlcs": {
    "501510": {
      "Name": "Crush Your Enemies - Plundered Loot DLC",
      "ImageUrl": "https://steamcdn-a.akamaihd.net/steam/apps/501510/header.jpg?t=1505119757"
    }
  },
  "Name": "Crush Your Enemies",
  "AppId": "406850",
  "ImageUrl": "https://steamcdn-a.akamaihd.net/steam/apps/406850/header.jpg?t=1572517410",
  "Languages": [
    "english",
    "french",
    "german",
    "polish",
    "russian",
    "schinese"
  ],
  "Platforms": {
    "windows": true,
    "mac": true,
    "linux": true
  }
}