{
  "Dlcs": {
    "464840": {
      "Name": "",
      "ImageUrl": ""
    },
    "530660": {
      "Name": "Hatbox: Hatful Eight + 2 (SteamWorld Heist)",
      "ImageUrl": "https://steamcdn-a.akamaihd.net/steam/apps/530660/header.jpg?t=1587121120"
    },
    "530661": {
      "Name": "Hatbox: Three 4 Free (SteamWorld Heist)",
      "ImageUrl": "https://steamcdn-a.akamaihd.net/steam/apps/530661/header.jpg?t=1529071041"
    },
    "490320": {
      "Name": "Music from SteamWorld Heist - Steam Powered Giraffe",
      "ImageUrl": "https://steamcdn-a.akamaihd.net/steam/apps/490320/header.jpg?t=1529582379"
    }
  },
  "Name": "SteamWorld Heist",
  "AppId": "322190",
  "ImageUrl": "https://steamcdn-a.akamaihd.net/steam/apps/322190/header.jpg?t=1587121034",
  "Languages": [
    "english",
    "french",
    "italian",
    "german",
    "spanish",
    "russian"
  ],
  "Platforms": {
    "windows": true,
    "mac": true,
    "linux": true
  }
}