{
  "Dlcs": {
    "650900": {
      "Name": "Teslagrad - Soundtrack",
      "ImageUrl": "https://cdn.akamai.steamstatic.com/steam/apps/650900/header.jpg?t=1611236360",
      "Type": "dlc"
    }
  },
  "Name": "Teslagrad",
  "AppId": "249590",
  "ImageUrl": "https://cdn.akamai.steamstatic.com/steam/apps/249590/header.jpg?t=1611235369",
  "Languages": [
    "english",
    "italian",
    "german",
    "dutch",
    "norwegian",
    "portuguese",
    "portuguese",
    "russian",
    "french",
    "spanish",
    "polish",
    "arabic",
    "turkish",
    "ukrainian",
    "schinese"
  ],
  "Platforms": {
    "windows": true,
    "mac": true,
    "linux": true
  }
}