{
  "Dlcs": {
    "955990": {
      "Name": "Cave Digger: Supporter's Pack",
      "ImageUrl": "https://cdn.akamai.steamstatic.com/steam/apps/955990/header.jpg?t=1577129183",
      "Type": "dlc"
    }
  },
  "Name": "Cave Digger VR",
  "AppId": "844380",
  "ImageUrl": "https://cdn.akamai.steamstatic.com/steam/apps/844380/header.jpg?t=1619774832",
  "Languages": [
    "english",
    "schinese",
    "german",
    "spanish",
    "korean",
    "tchinese"
  ],
  "Platforms": {
    "windows": true,
    "mac": false,
    "linux": false
  }
}