{
  "Dlcs": {
    "1084940": {
      "Name": "《叙事曲2：星空下的诺言》原声音轨 / Ballade2: the Celestial Promise - Original Soundtrack",
      "ImageUrl": "https://steamcdn-a.akamaihd.net/steam/apps/1084940/header.jpg?t=1558376989"
    }
  },
  "Name": "叙事曲2：星空下的诺言 / Ballade2: the Celestial Promise",
  "AppId": "1080990",
  "ImageUrl": "https://steamcdn-a.akamaihd.net/steam/apps/1080990/header.jpg?t=1576656880",
  "Languages": [
    "schinese",
    "tchinese"
  ],
  "Platforms": {
    "windows": true,
    "mac": true,
    "linux": false
  }
}