{
  "Dlcs": {
    "759230": {
      "Name": "Steam: Rails to Riches - Southwestern France Map",
      "ImageUrl": "https://steamcdn-a.akamaihd.net/steam/apps/759230/header.jpg?t=1541816689"
    },
    "596820": {
      "Name": "Steam: Rails to Riches - Carcassonne Map",
      "ImageUrl": "https://steamcdn-a.akamaihd.net/steam/apps/596820/header.jpg?t=1541816684"
    },
    "596821": {
      "Name": "Steam: Rails to Riches - USA-Canada Map",
      "ImageUrl": "https://steamcdn-a.akamaihd.net/steam/apps/596821/header.jpg?t=1541816686"
    },
    "596822": {
      "Name": "Steam: Rails to Riches - Northern England Map",
      "ImageUrl": "https://steamcdn-a.akamaihd.net/steam/apps/596822/header.jpg?t=1542869455"
    },
    "596823": {
      "Name": "Steam: Rails to Riches - Belgium & Luxembourg Map",
      "ImageUrl": "https://steamcdn-a.akamaihd.net/steam/apps/596823/header.jpg?t=1541816687"
    }
  },
  "Name": "Steam: Rails to Riches",
  "AppId": "595930",
  "ImageUrl": "https://steamcdn-a.akamaihd.net/steam/apps/595930/header.jpg?t=1565263888",
  "Languages": [
    "english",
    "french",
    "italian",
    "german",
    "spanish",
    "tchinese",
    "schinese",
    "dutch",
    "japanese",
    "korean",
    "polish",
    "portuguese"
  ],
  "Platforms": {
    "windows": true,
    "mac": true,
    "linux": true
  }
}