[
  {
    "name": "s1_s1",
    "defaultvalue": 0,
    "displayName": "Reaction Trainer"
  },
  {
    "name": "s2_s2",
    "defaultvalue": 0,
    "displayName": "Bouncers"
  },
  {
    "name": "s3_s3",
    "defaultvalue": 0,
    "displayName": "Chasers"
  },
  {
    "name": "s4_s4",
    "defaultvalue": 0,
    "displayName": "Barrier Chase"
  },
  {
    "name": "s5_s5",
    "defaultvalue": 0,
    "displayName": "Three's A Crowd"
  },
  {
    "name": "s6_s6",
    "defaultvalue": 0,
    "displayName": "Tactical Village"
  },
  {
    "name": "s7_s7",
    "defaultvalue": 0,
    "displayName": "They Grow On You"
  },
  {
    "name": "s8_s8",
    "defaultvalue": 0,
    "displayName": "Bouncing Strategic"
  },
  {
    "name": "s9_s9",
    "defaultvalue": 0,
    "displayName": "Trails In Darkness"
  },
  {
    "name": "s10_s10",
    "defaultvalue": 0,
    "displayName": "In The Deep End"
  },
  {
    "name": "s11_s11",
    "defaultvalue": 0,
    "displayName": "Mass Harassment"
  },
  {
    "name": "s12_s12",
    "defaultvalue": 0,
    "displayName": "Zomballs 2"
  },
  {
    "name": "s13_s13",
    "defaultvalue": 0,
    "displayName": "A Bullet Bashing"
  },
  {
    "name": "s14_s14",
    "defaultvalue": 0,
    "displayName": "Growing Pains"
  },
  {
    "name": "s15_s15",
    "defaultvalue": 0,
    "displayName": "Watch Your Six"
  },
  {
    "name": "s16_s16",
    "defaultvalue": 0,
    "displayName": "What Grows Up"
  },
  {
    "name": "s17_s17",
    "defaultvalue": 0,
    "displayName": "Triple Threat"
  },
  {
    "name": "s20_s20",
    "defaultvalue": 0,
    "displayName": "All Of The Things"
  },
  {
    "name": "s21_s21",
    "defaultvalue": 0,
    "displayName": "Reaction Extreme"
  },
  {
    "name": "s24_s24",
    "defaultvalue": 0,
    "displayName": "Mine Those Turrets"
  },
  {
    "name": "s25_s25",
    "defaultvalue": 0,
    "displayName": "Super Sneaky"
  },
  {
    "name": "s26_s26",
    "defaultvalue": 0,
    "displayName": "Quick Hecticism"
  },
  {
    "name": "s27_s27",
    "defaultvalue": 0,
    "displayName": "Spice Of Life"
  },
  {
    "name": "s28_s28",
    "defaultvalue": 0,
    "displayName": "Bouncer Bedlam"
  },
  {
    "name": "s29_s29",
    "defaultvalue": 0,
    "displayName": "Turbo Minefield"
  },
  {
    "name": "s30_s30",
    "defaultvalue": 0,
    "displayName": "Zomballs Extreme"
  },
  {
    "name": "s31_s31",
    "defaultvalue": 0,
    "displayName": "Bounce Core"
  },
  {
    "name": "s32_s32",
    "defaultvalue": 0,
    "displayName": "Growing Mental"
  },
  {
    "name": "s33_s33",
    "defaultvalue": 0,
    "displayName": "Hardcore Classic"
  },
  {
    "name": "s34_s34",
    "defaultvalue": 0,
    "displayName": "Quick As You Can"
  },
  {
    "name": "s35_s35",
    "defaultvalue": 0,
    "displayName": "Hardcore 1's And 2's"
  },
  {
    "name": "s36_s36",
    "defaultvalue": 0,
    "displayName": "Chase Down"
  },
  {
    "name": "s37_s37",
    "defaultvalue": 0,
    "displayName": "Triple Core"
  },
  {
    "name": "s38_s38",
    "defaultvalue": 0,
    "displayName": "Gun Run"
  },
  {
    "name": "s39_s39",
    "defaultvalue": 0,
    "displayName": "Trail Blazer"
  },
  {
    "name": "s40_s40",
    "defaultvalue": 0,
    "displayName": "Stupid"
  },
  {
    "name": "s41_s41",
    "defaultvalue": 0,
    "displayName": "Bouncing Ridiculous"
  },
  {
    "name": "s42_s42",
    "defaultvalue": 0,
    "displayName": "All The Twos"
  },
  {
    "name": "s43_s43",
    "defaultvalue": 0,
    "displayName": "Barrier Mayhem"
  },
  {
    "name": "s44_s44",
    "defaultvalue": 0,
    "displayName": "All The Threes"
  },
  {
    "name": "s45_s45",
    "defaultvalue": 0,
    "displayName": "Speed Modification"
  },
  {
    "name": "s46_s46",
    "defaultvalue": 0,
    "displayName": "Super Sneaky Plus"
  },
  {
    "name": "s47_s47",
    "defaultvalue": 0,
    "displayName": "Intense Closure"
  },
  {
    "name": "s48_s48",
    "defaultvalue": 0,
    "displayName": "Tripler Blanket"
  },
  {
    "name": "s49_s49",
    "defaultvalue": 0,
    "displayName": "Bullet Hell"
  },
  {
    "name": "s50_s50",
    "defaultvalue": 0,
    "displayName": "Utter Mayhem"
  },
  {
    "name": "s51_s51",
    "defaultvalue": 0,
    "displayName": "Relentless Reaction Trainer"
  },
  {
    "name": "s52_s52",
    "defaultvalue": 0,
    "displayName": "Relentless Bouncers"
  },
  {
    "name": "s53_s53",
    "defaultvalue": 0,
    "displayName": "Relentless Chasers"
  },
  {
    "name": "s54_s54",
    "defaultvalue": 0,
    "displayName": "Relentless Barrier Chase"
  },
  {
    "name": "s55_s55",
    "defaultvalue": 0,
    "displayName": "Relentless Three's A Crowd"
  },
  {
    "name": "s56_s56",
    "defaultvalue": 0,
    "displayName": "Relentless Tactical Village"
  },
  {
    "name": "s57_s57",
    "defaultvalue": 0,
    "displayName": "Relentless They Grow On You"
  },
  {
    "name": "s58_s58",
    "defaultvalue": 0,
    "displayName": "Relentless Bouncing Strategic"
  },
  {
    "name": "s59_s59",
    "defaultvalue": 0,
    "displayName": "Relentless Trails In Darkness"
  },
  {
    "name": "s60_s60",
    "defaultvalue": 0,
    "displayName": "Relentless In The Deep End"
  },
  {
    "name": "s61_s61",
    "defaultvalue": 0,
    "displayName": "Relentless Mass Harassment"
  },
  {
    "name": "s62_s62",
    "defaultvalue": 0,
    "displayName": "Relentless Zomballs 2"
  },
  {
    "name": "s63_s63",
    "defaultvalue": 0,
    "displayName": "Relentless A Bullet Bashing"
  },
  {
    "name": "s64_s64",
    "defaultvalue": 0,
    "displayName": "Relentless Growing Pains"
  },
  {
    "name": "s65_s65",
    "defaultvalue": 0,
    "displayName": "Relentless Watch Your Six"
  },
  {
    "name": "s66_s66",
    "defaultvalue": 0,
    "displayName": "Relentless What Grows Up"
  },
  {
    "name": "s67_s67",
    "defaultvalue": 0,
    "displayName": "Relentless Triple Threat"
  },
  {
    "name": "s68_s68",
    "defaultvalue": 0,
    "displayName": "Relentless Variety Hour"
  },
  {
    "name": "s69_s69",
    "defaultvalue": 0,
    "displayName": "Relentless Watch Your Moves"
  },
  {
    "name": "s70_s70",
    "defaultvalue": 0,
    "displayName": "Relentless All Of The Things"
  },
  {
    "name": "s71_s71",
    "defaultvalue": 0,
    "displayName": "Relentless Reaction Extreme"
  },
  {
    "name": "s72_s72",
    "defaultvalue": 0,
    "displayName": "Relentless Defender"
  },
  {
    "name": "s73_s73",
    "defaultvalue": 0,
    "displayName": "Relentless Mega Barrier"
  },
  {
    "name": "s74_s74",
    "defaultvalue": 0,
    "displayName": "Relentless Mine Those Turrets"
  },
  {
    "name": "s75_s75",
    "defaultvalue": 0,
    "displayName": "Relentless Super Sneaky"
  },
  {
    "name": "s76_s76",
    "defaultvalue": 0,
    "displayName": "Relentless Quick Hecticism"
  },
  {
    "name": "s77_s77",
    "defaultvalue": 0,
    "displayName": "Relentless Spice Of Life"
  },
  {
    "name": "s78_s78",
    "defaultvalue": 0,
    "displayName": "Relentless Bouncer Bedlam"
  },
  {
    "name": "s79_s79",
    "defaultvalue": 0,
    "displayName": "Relentless Turbo Minefield"
  },
  {
    "name": "s80_s80",
    "defaultvalue": 0,
    "displayName": "Relentless Zomballs Extreme"
  },
  {
    "name": "s81_s81",
    "defaultvalue": 0,
    "displayName": "Relentless Bounce Core"
  },
  {
    "name": "s82_s82",
    "defaultvalue": 0,
    "displayName": "Relentless Growing Mental"
  },
  {
    "name": "s83_s83",
    "defaultvalue": 0,
    "displayName": "Relentless Hardcore Classic"
  },
  {
    "name": "s84_s84",
    "defaultvalue": 0,
    "displayName": "Relentless Quick As You Can"
  },
  {
    "name": "s85_s85",
    "defaultvalue": 0,
    "displayName": "Relentless Hardcore 1's And 2's"
  },
  {
    "name": "s86_s86",
    "defaultvalue": 0,
    "displayName": "Relentless Chase Down"
  },
  {
    "name": "s87_s87",
    "defaultvalue": 0,
    "displayName": "Relentless Triple Core"
  },
  {
    "name": "s88_s88",
    "defaultvalue": 0,
    "displayName": "Relentless Gun Run"
  },
  {
    "name": "s89_s89",
    "defaultvalue": 0,
    "displayName": "Relentless Trail Blazer"
  },
  {
    "name": "s90_s90",
    "defaultvalue": 0,
    "displayName": "Relentless Stupid"
  },
  {
    "name": "s91_s91",
    "defaultvalue": 0,
    "displayName": "Relentless Bouncing Ridiculous"
  },
  {
    "name": "s92_s92",
    "defaultvalue": 0,
    "displayName": "Relentless All The Twos"
  },
  {
    "name": "s93_s93",
    "defaultvalue": 0,
    "displayName": "Relentless Barrier Mayhem"
  },
  {
    "name": "s94_s94",
    "defaultvalue": 0,
    "displayName": "Relentless All The Threes"
  },
  {
    "name": "s95_s95",
    "defaultvalue": 0,
    "displayName": "Relentless Speed Modification"
  },
  {
    "name": "s96_s96",
    "defaultvalue": 0,
    "displayName": "Relentless Super Sneaky Plus"
  },
  {
    "name": "s97_s97",
    "defaultvalue": 0,
    "displayName": "Relentless Intense Closure"
  },
  {
    "name": "s98_s98",
    "defaultvalue": 0,
    "displayName": "Relentless Tripler Blanket"
  },
  {
    "name": "s99_s99",
    "defaultvalue": 0,
    "displayName": "Relentless Bullet Hell"
  },
  {
    "name": "s100_s100",
    "defaultvalue": 0,
    "displayName": "Relentless Utter Mayhem"
  },
  {
    "name": "m1_m1",
    "defaultvalue": 0,
    "displayName": "Multi - Reaction Trainer"
  },
  {
    "name": "m2_m2",
    "defaultvalue": 0,
    "displayName": "Multi - Bouncers"
  },
  {
    "name": "m3_m3",
    "defaultvalue": 0,
    "displayName": "Multi - Chasers"
  },
  {
    "name": "m4_m4",
    "defaultvalue": 0,
    "displayName": "Multi - Barrier Chase"
  },
  {
    "name": "m5_m5",
    "defaultvalue": 0,
    "displayName": "Multi - Three's A Crowd"
  },
  {
    "name": "m6_m6",
    "defaultvalue": 0,
    "displayName": "Multi - Tactical Village"
  },
  {
    "name": "m7_m7",
    "defaultvalue": 0,
    "displayName": "Multi - They Grow On You"
  },
  {
    "name": "m8_m8",
    "defaultvalue": 0,
    "displayName": "Multi - Bouncing Strategic"
  },
  {
    "name": "m9_m9",
    "defaultvalue": 0,
    "displayName": "Multi - Trails In Darkness"
  },
  {
    "name": "m10_m10",
    "defaultvalue": 0,
    "displayName": "Multi - In The Deep End"
  },
  {
    "name": "m11_m11",
    "defaultvalue": 0,
    "displayName": "Multi - Mass Harassment"
  },
  {
    "name": "m12_m12",
    "defaultvalue": 0,
    "displayName": "Multi - Zomballs 2"
  },
  {
    "name": "m13_m13",
    "defaultvalue": 0,
    "displayName": "Multi - A Bullet Bashing"
  },
  {
    "name": "m14_m14",
    "defaultvalue": 0,
    "displayName": "Multi - Growing Pains"
  },
  {
    "name": "m15_m15",
    "defaultvalue": 0,
    "displayName": "Multi - Watch Your Six"
  },
  {
    "name": "m16_m16",
    "defaultvalue": 0,
    "displayName": "Multi - What Grows Up"
  },
  {
    "name": "m17_m17",
    "defaultvalue": 0,
    "displayName": "Multi - Triple Threat"
  },
  {
    "name": "m18_m18",
    "defaultvalue": 0,
    "displayName": "Multi - Variety Hour"
  },
  {
    "name": "m19_m19",
    "defaultvalue": 0,
    "displayName": "Multi - Watch Your Moves"
  },
  {
    "name": "m20_m20",
    "defaultvalue": 0,
    "displayName": "Multi - All Of The Things"
  },
  {
    "name": "m21_m21",
    "defaultvalue": 0,
    "displayName": "Multi - Reaction Extreme"
  },
  {
    "name": "m22_m22",
    "defaultvalue": 0,
    "displayName": "Multi - Defender"
  },
  {
    "name": "m23_m23",
    "defaultvalue": 0,
    "displayName": "Multi - Mega Barrier"
  },
  {
    "name": "m24_m24",
    "defaultvalue": 0,
    "displayName": "Multi - Mine Those Turrets"
  },
  {
    "name": "m25_m25",
    "defaultvalue": 0,
    "displayName": "Multi - Super Sneaky"
  },
  {
    "name": "m26_m26",
    "defaultvalue": 0,
    "displayName": "Multi - Quick Hecticism"
  },
  {
    "name": "m27_m27",
    "defaultvalue": 0,
    "displayName": "Multi - Spice Of Life"
  },
  {
    "name": "m28_m28",
    "defaultvalue": 0,
    "displayName": "Multi - Bouncer Bedlam"
  },
  {
    "name": "m29_m29",
    "defaultvalue": 0,
    "displayName": "Multi - Turbo Minefield"
  },
  {
    "name": "m30_m30",
    "defaultvalue": 0,
    "displayName": "Multi - Zomballs Extreme"
  },
  {
    "name": "m31_m31",
    "defaultvalue": 0,
    "displayName": "Multi - Bounce Core"
  },
  {
    "name": "m32_m32",
    "defaultvalue": 0,
    "displayName": "Multi - Growing Mental"
  },
  {
    "name": "m33_m33",
    "defaultvalue": 0,
    "displayName": "Multi - Hardcore Classic"
  },
  {
    "name": "m34_m34",
    "defaultvalue": 0,
    "displayName": "Multi - Quick As You Can"
  },
  {
    "name": "m35_m35",
    "defaultvalue": 0,
    "displayName": "Multi - Hardcore 1's And 2's"
  },
  {
    "name": "m36_m36",
    "defaultvalue": 0,
    "displayName": "Multi - Chase Down"
  },
  {
    "name": "m37_m37",
    "defaultvalue": 0,
    "displayName": "Multi - Triple Core"
  },
  {
    "name": "m38_m38",
    "defaultvalue": 0,
    "displayName": "Multi - Gun Run"
  },
  {
    "name": "m39_m39",
    "defaultvalue": 0,
    "displayName": "Multi - Trail Blazer"
  },
  {
    "name": "m40_m40",
    "defaultvalue": 0,
    "displayName": "Multi - Stupid"
  },
  {
    "name": "m41_m41",
    "defaultvalue": 0,
    "displayName": "Multi - Bouncing Ridiculous"
  },
  {
    "name": "m42_m42",
    "defaultvalue": 0,
    "displayName": "Multi - All The Twos"
  },
  {
    "name": "m43_m43",
    "defaultvalue": 0,
    "displayName": "Multi - Barrier Mayhem"
  },
  {
    "name": "m44_m44",
    "defaultvalue": 0,
    "displayName": "Multi - All The Threes"
  },
  {
    "name": "m45_m45",
    "defaultvalue": 0,
    "displayName": "Multi - Speed Modification"
  },
  {
    "name": "m46_m46",
    "defaultvalue": 0,
    "displayName": "Multi - Super Sneaky Plus"
  },
  {
    "name": "m47_m47",
    "defaultvalue": 0,
    "displayName": "Multi - Intense Closure"
  },
  {
    "name": "m48_m48",
    "defaultvalue": 0,
    "displayName": "Multi - Tripler Blanket"
  },
  {
    "name": "m49_m49",
    "defaultvalue": 0,
    "displayName": "Multi - Bullet Hell"
  },
  {
    "name": "m50_m50",
    "defaultvalue": 0,
    "displayName": "Multi - Utter Mayhem"
  },
  {
    "name": "m51_m51",
    "defaultvalue": 0,
    "displayName": "Multi - Relentless Reaction Trainer"
  },
  {
    "name": "m52_m52",
    "defaultvalue": 0,
    "displayName": "Multi - Relentless Bouncers"
  },
  {
    "name": "m53_m53",
    "defaultvalue": 0,
    "displayName": "Multi - Relentless Chasers"
  },
  {
    "name": "m54_m54",
    "defaultvalue": 0,
    "displayName": "Multi - Relentless Barrier Chase"
  },
  {
    "name": "m55_m55",
    "defaultvalue": 0,
    "displayName": "Multi - Relentless Three's A Crowd"
  },
  {
    "name": "m56_m56",
    "defaultvalue": 0,
    "displayName": "Multi - Relentless Tactical Village"
  },
  {
    "name": "m57_m57",
    "defaultvalue": 0,
    "displayName": "Multi - Relentless They Grow On You"
  },
  {
    "name": "m58_m58",
    "defaultvalue": 0,
    "displayName": "Multi - Relentless Bouncing Strategic"
  },
  {
    "name": "m59_m59",
    "defaultvalue": 0,
    "displayName": "Multi - Relentless Trails In Darkness"
  },
  {
    "name": "m60_m60",
    "defaultvalue": 0,
    "displayName": "Multi - Relentless In The Deep End"
  },
  {
    "name": "m61_m61",
    "defaultvalue": 0,
    "displayName": "Multi - Relentless Mass Harassment"
  },
  {
    "name": "m62_m62",
    "defaultvalue": 0,
    "displayName": "Multi - Relentless Zomballs 2"
  },
  {
    "name": "m63_m63",
    "defaultvalue": 0,
    "displayName": "Multi - Relentless A Bullet Bashing"
  },
  {
    "name": "m64_m64",
    "defaultvalue": 0,
    "displayName": "Multi - Relentless Growing Pains"
  },
  {
    "name": "m65_m65",
    "defaultvalue": 0,
    "displayName": "Multi - Relentless Watch Your Six"
  },
  {
    "name": "m66_m66",
    "defaultvalue": 0,
    "displayName": "Multi - Relentless What Grows Up"
  },
  {
    "name": "m67_m67",
    "defaultvalue": 0,
    "displayName": "Multi - Relentless Triple Threat"
  },
  {
    "name": "m68_m68",
    "defaultvalue": 0,
    "displayName": "Multi - Relentless Variety Hour"
  },
  {
    "name": "m69_m69",
    "defaultvalue": 0,
    "displayName": "Multi - Relentless Watch Your Moves"
  },
  {
    "name": "m70_m70",
    "defaultvalue": 0,
    "displayName": "Multi - Relentless All Of The Things"
  },
  {
    "name": "m71_m71",
    "defaultvalue": 0,
    "displayName": "Multi - Relentless Reaction Extreme"
  },
  {
    "name": "m72_m72",
    "defaultvalue": 0,
    "displayName": "Multi - Relentless Defender"
  },
  {
    "name": "m73_m73",
    "defaultvalue": 0,
    "displayName": "Multi - Relentless Mega Barrier"
  },
  {
    "name": "m74_m74",
    "defaultvalue": 0,
    "displayName": "Multi - Relentless Mine Those Turrets"
  },
  {
    "name": "m75_m75",
    "defaultvalue": 0,
    "displayName": "Multi - Relentless Super Sneaky"
  },
  {
    "name": "m76_m76",
    "defaultvalue": 0,
    "displayName": "Multi - Relentless Quick Hecticism"
  },
  {
    "name": "m77_m77",
    "defaultvalue": 0,
    "displayName": "Multi - Relentless Spice Of Life"
  },
  {
    "name": "m78_m78",
    "defaultvalue": 0,
    "displayName": "Multi - Relentless Bouncer Bedlam"
  },
  {
    "name": "m79_m79",
    "defaultvalue": 0,
    "displayName": "Multi - Relentless Turbo Minefield"
  },
  {
    "name": "m80_m80",
    "defaultvalue": 0,
    "displayName": "Multi - Relentless Zomballs Extreme"
  },
  {
    "name": "m81_m81",
    "defaultvalue": 0,
    "displayName": "Multi - Relentless Bounce Core"
  },
  {
    "name": "m82_m82",
    "defaultvalue": 0,
    "displayName": "Multi - Relentless Growing Mental"
  },
  {
    "name": "m83_m83",
    "defaultvalue": 0,
    "displayName": "Multi - Relentless Hardcore Classic"
  },
  {
    "name": "m84_m84",
    "defaultvalue": 0,
    "displayName": "Multi - Relentless Quick As You Can"
  },
  {
    "name": "m85_m85",
    "defaultvalue": 0,
    "displayName": "Multi - Relentless Hardcore 1's And 2's"
  },
  {
    "name": "m86_m86",
    "defaultvalue": 0,
    "displayName": "Multi - Relentless Chase Down"
  },
  {
    "name": "m87_m87",
    "defaultvalue": 0,
    "displayName": "Multi - Relentless Triple Core"
  },
  {
    "name": "m88_m88",
    "defaultvalue": 0,
    "displayName": "Multi - Relentless Gun Run"
  },
  {
    "name": "m89_m89",
    "defaultvalue": 0,
    "displayName": "Multi - Relentless Trail Blazer"
  },
  {
    "name": "m90_m90",
    "defaultvalue": 0,
    "displayName": "Multi - Relentless Stupid"
  },
  {
    "name": "m91_m91",
    "defaultvalue": 0,
    "displayName": "Multi - Relentless Bouncing Ridiculous"
  },
  {
    "name": "m92_m92",
    "defaultvalue": 0,
    "displayName": "Multi - Relentless All The Twos"
  },
  {
    "name": "m93_m93",
    "defaultvalue": 0,
    "displayName": "Multi - Relentless Barrier Mayhem"
  },
  {
    "name": "m94_m94",
    "defaultvalue": 0,
    "displayName": "Multi - Relentless All The Threes"
  },
  {
    "name": "m95_m95",
    "defaultvalue": 0,
    "displayName": "Multi - Relentless Speed Modification"
  },
  {
    "name": "m96_m96",
    "defaultvalue": 0,
    "displayName": "Multi - Relentless Super Sneaky Plus"
  },
  {
    "name": "m97_m97",
    "defaultvalue": 0,
    "displayName": "Multi - Relentless Intense Closure"
  },
  {
    "name": "m98_m98",
    "defaultvalue": 0,
    "displayName": "Multi - Relentless Tripler Blanket"
  },
  {
    "name": "m99_m99",
    "defaultvalue": 0,
    "displayName": "Multi - Relentless Bullet Hell"
  },
  {
    "name": "m100_m100",
    "defaultvalue": 0,
    "displayName": "Multi - Relentless Utter Mayhem"
  },
  {
    "name": "m2p1_m2p1",
    "defaultvalue": 0,
    "displayName": "Coop2 - Reaction Trainer"
  },
  {
    "name": "m2p2_m2p2",
    "defaultvalue": 0,
    "displayName": "Coop2 - Bouncers"
  },
  {
    "name": "m2p3_m2p3",
    "defaultvalue": 0,
    "displayName": "Coop2 - Chasers"
  },
  {
    "name": "m2p4_m2p4",
    "defaultvalue": 0,
    "displayName": "Coop2 - Barrier Chase"
  },
  {
    "name": "m2p5_m2p5",
    "defaultvalue": 0,
    "displayName": "Coop2 - Three's A Crowd"
  },
  {
    "name": "m2p6_m2p6",
    "defaultvalue": 0,
    "displayName": "Coop2 - Tactical Village"
  },
  {
    "name": "m2p7_m2p7",
    "defaultvalue": 0,
    "displayName": "Coop2 - They Grow On You"
  },
  {
    "name": "m2p8_m2p8",
    "defaultvalue": 0,
    "displayName": "Coop2 - Bouncing Strategic"
  },
  {
    "name": "m2p9_m2p9",
    "defaultvalue": 0,
    "displayName": "Coop2 - Trails In Darkness"
  },
  {
    "name": "m2p10_m2p10",
    "defaultvalue": 0,
    "displayName": "Coop2 - In The Deep End"
  },
  {
    "name": "m2p11_m2p11",
    "defaultvalue": 0,
    "displayName": "Coop2 - Mass Harassment"
  },
  {
    "name": "m2p12_m2p12",
    "defaultvalue": 0,
    "displayName": "Coop2 - Zomballs 2"
  },
  {
    "name": "m2p13_m2p13",
    "defaultvalue": 0,
    "displayName": "Coop2 - A Bullet Bashing"
  },
  {
    "name": "m2p14_m2p14",
    "defaultvalue": 0,
    "displayName": "Coop2 - Growing Pains"
  },
  {
    "name": "m2p15_m2p15",
    "defaultvalue": 0,
    "displayName": "Coop2 - Watch Your Six"
  },
  {
    "name": "m2p16_m2p16",
    "defaultvalue": 0,
    "displayName": "Coop2 - What Grows Up"
  },
  {
    "name": "m2p17_m2p17",
    "defaultvalue": 0,
    "displayName": "Coop2 - Triple Threat"
  },
  {
    "name": "m2p18_m2p18",
    "defaultvalue": 0,
    "displayName": "Coop2 - Variety Hour"
  },
  {
    "name": "m2p19_m2p19",
    "defaultvalue": 0,
    "displayName": "Coop2 - Watch Your Moves"
  },
  {
    "name": "m2p20_m2p20",
    "defaultvalue": 0,
    "displayName": "Coop2 - All Of The Things"
  },
  {
    "name": "m2p21_m2p21",
    "defaultvalue": 0,
    "displayName": "Coop2 - Reaction Extreme"
  },
  {
    "name": "m2p22_m2p22",
    "defaultvalue": 0,
    "displayName": "Coop2 - Defender"
  },
  {
    "name": "m2p23_m2p23",
    "defaultvalue": 0,
    "displayName": "Coop2 - Mega Barrier"
  },
  {
    "name": "m2p24_m2p24",
    "defaultvalue": 0,
    "displayName": "Coop2 - Mine Those Turrets"
  },
  {
    "name": "m2p25_m2p25",
    "defaultvalue": 0,
    "displayName": "Coop2 - Super Sneaky"
  },
  {
    "name": "m2p26_m2p26",
    "defaultvalue": 0,
    "displayName": "Coop2 - Quick Hecticism"
  },
  {
    "name": "m2p27_m2p27",
    "defaultvalue": 0,
    "displayName": "Coop2 - Spice Of Life"
  },
  {
    "name": "m2p28_m2p28",
    "defaultvalue": 0,
    "displayName": "Coop2 - Bouncer Bedlam"
  },
  {
    "name": "m2p29_m2p29",
    "defaultvalue": 0,
    "displayName": "Coop2 - Turbo Minefield"
  },
  {
    "name": "m2p30_m2p30",
    "defaultvalue": 0,
    "displayName": "Coop2 - Zomballs Extreme"
  },
  {
    "name": "m2p31_m2p31",
    "defaultvalue": 0,
    "displayName": "Coop2 - Bounce Core"
  },
  {
    "name": "m2p32_m2p32",
    "defaultvalue": 0,
    "displayName": "Coop2 - Growing Mental"
  },
  {
    "name": "m2p33_m2p33",
    "defaultvalue": 0,
    "displayName": "Coop2 - Hardcore Classic"
  },
  {
    "name": "m2p34_m2p34",
    "defaultvalue": 0,
    "displayName": "Coop2 - Quick As You Can"
  },
  {
    "name": "m2p35_m2p35",
    "defaultvalue": 0,
    "displayName": "Coop2 - Hardcore 1's And 2's"
  },
  {
    "name": "m2p36_m2p36",
    "defaultvalue": 0,
    "displayName": "Coop2 - Chase Down"
  },
  {
    "name": "m2p37_m2p37",
    "defaultvalue": 0,
    "displayName": "Coop2 - Triple Core"
  },
  {
    "name": "m2p38_m2p38",
    "defaultvalue": 0,
    "displayName": "Coop2 - Gun Run"
  },
  {
    "name": "m2p39_m2p39",
    "defaultvalue": 0,
    "displayName": "Coop2 - Trail Blazer"
  },
  {
    "name": "m2p40_m2p40",
    "defaultvalue": 0,
    "displayName": "Coop2 - Stupid"
  },
  {
    "name": "m2p41_m2p41",
    "defaultvalue": 0,
    "displayName": "Coop2 - Bouncing Ridiculous"
  },
  {
    "name": "m2p42_m2p42",
    "defaultvalue": 0,
    "displayName": "Coop2 - All The Twos"
  },
  {
    "name": "m2p43_m2p43",
    "defaultvalue": 0,
    "displayName": "Coop2 - Barrier Mayhem"
  },
  {
    "name": "m2p44_m2p44",
    "defaultvalue": 0,
    "displayName": "Coop2 - All The Threes"
  },
  {
    "name": "m2p45_m2p45",
    "defaultvalue": 0,
    "displayName": "Coop2 - Speed Modification"
  },
  {
    "name": "m2p46_m2p46",
    "defaultvalue": 0,
    "displayName": "Coop2 - Super Sneaky Plus"
  },
  {
    "name": "m2p47_m2p47",
    "defaultvalue": 0,
    "displayName": "Coop2 - Intense Closure"
  },
  {
    "name": "m2p48_m2p48",
    "defaultvalue": 0,
    "displayName": "Coop2 - Tripler Blanket"
  },
  {
    "name": "m2p49_m2p49",
    "defaultvalue": 0,
    "displayName": "Coop2 - Bullet Hell"
  },
  {
    "name": "m2p50_m2p50",
    "defaultvalue": 0,
    "displayName": "Coop2 - Utter Mayhem"
  },
  {
    "name": "m2p51_m2p51",
    "defaultvalue": 0,
    "displayName": "Coop2 - Relentless Reaction Trainer"
  },
  {
    "name": "m2p52_m2p52",
    "defaultvalue": 0,
    "displayName": "Coop2 - Relentless Bouncers"
  },
  {
    "name": "m2p53_m2p53",
    "defaultvalue": 0,
    "displayName": "Coop2 - Relentless Chasers"
  },
  {
    "name": "m2p54_m2p54",
    "defaultvalue": 0,
    "displayName": "Coop2 - Relentless Barrier Chase"
  },
  {
    "name": "m2p55_m2p55",
    "defaultvalue": 0,
    "displayName": "Coop2 - Relentless Three's A Crowd"
  },
  {
    "name": "m2p56_m2p56",
    "defaultvalue": 0,
    "displayName": "Coop2 - Relentless Tactical Village"
  },
  {
    "name": "m2p57_m2p57",
    "defaultvalue": 0,
    "displayName": "Coop2 - Relentless They Grow On You"
  },
  {
    "name": "m2p58_m2p58",
    "defaultvalue": 0,
    "displayName": "Coop2 - Relentless Bouncing Strategic"
  },
  {
    "name": "m2p59_m2p59",
    "defaultvalue": 0,
    "displayName": "Coop2 - Relentless Trails In Darkness"
  },
  {
    "name": "m2p60_m2p60",
    "defaultvalue": 0,
    "displayName": "Coop2 - Relentless In The Deep End"
  },
  {
    "name": "m2p61_m2p61",
    "defaultvalue": 0,
    "displayName": "Coop2 - Relentless Mass Harassment"
  },
  {
    "name": "m2p62_m2p62",
    "defaultvalue": 0,
    "displayName": "Coop2 - Relentless Zomballs 2"
  },
  {
    "name": "m2p63_m2p63",
    "defaultvalue": 0,
    "displayName": "Coop2 - Relentless A Bullet Bashing"
  },
  {
    "name": "m2p64_m2p64",
    "defaultvalue": 0,
    "displayName": "Coop2 - Relentless Growing Pains"
  },
  {
    "name": "m2p65_m2p65",
    "defaultvalue": 0,
    "displayName": "Coop2 - Relentless Watch Your Six"
  },
  {
    "name": "m2p66_m2p66",
    "defaultvalue": 0,
    "displayName": "Coop2 - Relentless What Grows Up"
  },
  {
    "name": "m2p67_m2p67",
    "defaultvalue": 0,
    "displayName": "Coop2 - Relentless Triple Threat"
  },
  {
    "name": "m2p68_m2p68",
    "defaultvalue": 0,
    "displayName": "Coop2 - Relentless Variety Hour"
  },
  {
    "name": "m2p69_m2p69",
    "defaultvalue": 0,
    "displayName": "Coop2 - Relentless Watch Your Moves"
  },
  {
    "name": "m2p70_m2p70",
    "defaultvalue": 0,
    "displayName": "Coop2 - Relentless All Of The Things"
  },
  {
    "name": "m2p71_m2p71",
    "defaultvalue": 0,
    "displayName": "Coop2 - Relentless Reaction Extreme"
  },
  {
    "name": "m2p72_m2p72",
    "defaultvalue": 0,
    "displayName": "Coop2 - Relentless Defender"
  },
  {
    "name": "m2p73_m2p73",
    "defaultvalue": 0,
    "displayName": "Coop2 - Relentless Mega Barrier"
  },
  {
    "name": "m2p74_m2p74",
    "defaultvalue": 0,
    "displayName": "Coop2 - Relentless Mine Those Turrets"
  },
  {
    "name": "m2p75_m2p75",
    "defaultvalue": 0,
    "displayName": "Coop2 - Relentless Super Sneaky"
  },
  {
    "name": "m2p76_m2p76",
    "defaultvalue": 0,
    "displayName": "Coop2 - Relentless Quick Hecticism"
  },
  {
    "name": "m2p77_m2p77",
    "defaultvalue": 0,
    "displayName": "Coop2 - Relentless Spice Of Life"
  },
  {
    "name": "m2p78_m2p78",
    "defaultvalue": 0,
    "displayName": "Coop2 - Relentless Bouncer Bedlam"
  },
  {
    "name": "m2p79_m2p79",
    "defaultvalue": 0,
    "displayName": "Coop2 - Relentless Turbo Minefield"
  },
  {
    "name": "m2p80_m2p80",
    "defaultvalue": 0,
    "displayName": "Coop2 - Relentless Zomballs Extreme"
  },
  {
    "name": "m2p81_m2p81",
    "defaultvalue": 0,
    "displayName": "Coop2 - Relentless Bounce Core"
  },
  {
    "name": "m2p82_m2p82",
    "defaultvalue": 0,
    "displayName": "Coop2 - Relentless Growing Mental"
  },
  {
    "name": "m2p83_m2p83",
    "defaultvalue": 0,
    "displayName": "Coop2 - Relentless Hardcore Classic"
  },
  {
    "name": "m2p84_m2p84",
    "defaultvalue": 0,
    "displayName": "Coop2 - Relentless Quick As You Can"
  },
  {
    "name": "m2p85_m2p85",
    "defaultvalue": 0,
    "displayName": "Coop2 - Relentless Hardcore 1's And 2's"
  },
  {
    "name": "m2p86_m2p86",
    "defaultvalue": 0,
    "displayName": "Coop2 - Relentless Chase Down"
  },
  {
    "name": "m2p87_m2p87",
    "defaultvalue": 0,
    "displayName": "Coop2 - Relentless Triple Core"
  },
  {
    "name": "m2p88_m2p88",
    "defaultvalue": 0,
    "displayName": "Coop2 - Relentless Gun Run"
  },
  {
    "name": "m2p89_m2p89",
    "defaultvalue": 0,
    "displayName": "Coop2 - Relentless Trail Blazer"
  },
  {
    "name": "m2p90_m2p90",
    "defaultvalue": 0,
    "displayName": "Coop2 - Relentless Stupid"
  },
  {
    "name": "m2p91_m2p91",
    "defaultvalue": 0,
    "displayName": "Coop2 - Relentless Bouncing Ridiculous"
  },
  {
    "name": "m2p93_m2p93",
    "defaultvalue": 0,
    "displayName": "Coop2 - Relentless Barrier Mayhem"
  },
  {
    "name": "m2p94_m2p94",
    "defaultvalue": 0,
    "displayName": "Coop2 - Relentless All The Threes"
  },
  {
    "name": "m2p95_m2p95",
    "defaultvalue": 0,
    "displayName": "Coop2 - Relentless Speed Modification"
  },
  {
    "name": "m2p97_m2p97",
    "defaultvalue": 0,
    "displayName": "Coop2 - Relentless Intense Closure"
  },
  {
    "name": "m2p99_m2p99",
    "defaultvalue": 0,
    "displayName": "Coop2 - Relentless Bullet Hell"
  },
  {
    "name": "m4p1_m4p1",
    "defaultvalue": 0,
    "displayName": "Coop4 - Reaction Trainer"
  },
  {
    "name": "m4p2_m4p2",
    "defaultvalue": 0,
    "displayName": "Coop4 - Bouncers"
  },
  {
    "name": "m4p3_m4p3",
    "defaultvalue": 0,
    "displayName": "Coop4 - Chasers"
  },
  {
    "name": "m4p4_m4p4",
    "defaultvalue": 0,
    "displayName": "Coop4 - Barrier Chase"
  },
  {
    "name": "m4p5_m4p5",
    "defaultvalue": 0,
    "displayName": "Coop4 - Three's A Crowd"
  },
  {
    "name": "m4p6_m4p6",
    "defaultvalue": 0,
    "displayName": "Coop4 - Tactical Village"
  },
  {
    "name": "m4p7_m4p7",
    "defaultvalue": 0,
    "displayName": "Coop4 - They Grow On You"
  },
  {
    "name": "m4p8_m4p8",
    "defaultvalue": 0,
    "displayName": "Coop4 - Bouncing Strategic"
  },
  {
    "name": "m4p9_m4p9",
    "defaultvalue": 0,
    "displayName": "Coop4 - Trails In Darkness"
  },
  {
    "name": "m4p10_m4p10",
    "defaultvalue": 0,
    "displayName": "Coop4 - In The Deep End"
  },
  {
    "name": "m4p11_m4p11",
    "defaultvalue": 0,
    "displayName": "Coop4 - Mass Harassment"
  },
  {
    "name": "m4p12_m4p12",
    "defaultvalue": 0,
    "displayName": "Coop4 - Zomballs 2"
  },
  {
    "name": "m4p13_m4p13",
    "defaultvalue": 0,
    "displayName": "Coop4 - A Bullet Bashing"
  },
  {
    "name": "m4p14_m4p14",
    "defaultvalue": 0,
    "displayName": "Coop4 - Growing Pains"
  },
  {
    "name": "m4p15_m4p15",
    "defaultvalue": 0,
    "displayName": "Coop4 - Watch Your Six"
  },
  {
    "name": "m4p16_m4p16",
    "defaultvalue": 0,
    "displayName": "Coop4 - What Grows Up"
  },
  {
    "name": "m4p17_m4p17",
    "defaultvalue": 0,
    "displayName": "Coop4 - Triple Threat"
  },
  {
    "name": "m4p18_m4p18",
    "defaultvalue": 0,
    "displayName": "Coop4 - Variety Hour"
  },
  {
    "name": "m4p19_m4p19",
    "defaultvalue": 0,
    "displayName": "Coop4 - Watch Your Moves"
  },
  {
    "name": "m4p20_m4p20",
    "defaultvalue": 0,
    "displayName": "Coop4 - All Of The Things"
  },
  {
    "name": "m4p21_m4p21",
    "defaultvalue": 0,
    "displayName": "Coop4 - Reaction Extreme"
  },
  {
    "name": "m4p22_m4p22",
    "defaultvalue": 0,
    "displayName": "Coop4 - Defender"
  },
  {
    "name": "m4p23_m4p23",
    "defaultvalue": 0,
    "displayName": "Coop4 - Mega Barrier"
  },
  {
    "name": "m4p24_m4p24",
    "defaultvalue": 0,
    "displayName": "Coop4 - Mine Those Turrets"
  },
  {
    "name": "m4p25_m4p25",
    "defaultvalue": 0,
    "displayName": "Coop4 - Super Sneaky"
  },
  {
    "name": "m4p26_m4p26",
    "defaultvalue": 0,
    "displayName": "Coop4 - Quick Hecticism"
  },
  {
    "name": "m4p27_m4p27",
    "defaultvalue": 0,
    "displayName": "Coop4 - Spice Of Life"
  },
  {
    "name": "m4p28_m4p28",
    "defaultvalue": 0,
    "displayName": "Coop4 - Bouncer Bedlam"
  },
  {
    "name": "m4p29_m4p29",
    "defaultvalue": 0,
    "displayName": "Coop4 - Turbo Minefield"
  },
  {
    "name": "m4p30_m4p30",
    "defaultvalue": 0,
    "displayName": "Coop4 - Zomballs Extreme"
  },
  {
    "name": "m4p31_m4p31",
    "defaultvalue": 0,
    "displayName": "Coop4 - Bounce Core"
  },
  {
    "name": "m4p32_m4p32",
    "defaultvalue": 0,
    "displayName": "Coop4 - Growing Mental"
  },
  {
    "name": "m4p33_m4p33",
    "defaultvalue": 0,
    "displayName": "Coop4 - Hardcore Classic"
  },
  {
    "name": "m4p34_m4p34",
    "defaultvalue": 0,
    "displayName": "Coop4 - Quick As You Can"
  },
  {
    "name": "m4p35_m4p35",
    "defaultvalue": 0,
    "displayName": "Coop4 - Hardcore 1's And 2's"
  },
  {
    "name": "m4p36_m4p36",
    "defaultvalue": 0,
    "displayName": "Coop4 - Chase Down"
  },
  {
    "name": "m4p37_m4p37",
    "defaultvalue": 0,
    "displayName": "Coop4 - Triple Core"
  },
  {
    "name": "m4p38_m4p38",
    "defaultvalue": 0,
    "displayName": "Coop4 - Gun Run"
  },
  {
    "name": "m4p39_m4p39",
    "defaultvalue": 0,
    "displayName": "Coop4 - Trail Blazer"
  },
  {
    "name": "m4p40_m4p40",
    "defaultvalue": 0,
    "displayName": "Coop4 - Stupid"
  },
  {
    "name": "m4p41_m4p41",
    "defaultvalue": 0,
    "displayName": "Coop4 - Bouncing Ridiculous"
  },
  {
    "name": "m4p42_m4p42",
    "defaultvalue": 0,
    "displayName": "Coop4 - All The Twos"
  },
  {
    "name": "m4p43_m4p43",
    "defaultvalue": 0,
    "displayName": "Coop4 - Barrier Mayhem"
  },
  {
    "name": "m4p44_m4p44",
    "defaultvalue": 0,
    "displayName": "Coop4 - All The Threes"
  },
  {
    "name": "m4p45_m4p45",
    "defaultvalue": 0,
    "displayName": "Coop4 - Speed Modification"
  },
  {
    "name": "m4p46_m4p46",
    "defaultvalue": 0,
    "displayName": "Coop4 - Super Sneaky Plus"
  },
  {
    "name": "m4p47_m4p47",
    "defaultvalue": 0,
    "displayName": "Coop4 - Intense Closure"
  },
  {
    "name": "m4p48_m4p48",
    "defaultvalue": 0,
    "displayName": "Coop4 - Tripler Blanket"
  },
  {
    "name": "m4p49_m4p49",
    "defaultvalue": 0,
    "displayName": "Coop4 - Bullet Hell"
  },
  {
    "name": "m4p50_m4p50",
    "defaultvalue": 0,
    "displayName": "Coop4 - Utter Mayhem"
  },
  {
    "name": "m4p51_m4p51",
    "defaultvalue": 0,
    "displayName": "Coop4 - Relentless Reaction Trainer"
  },
  {
    "name": "m4p52_m4p52",
    "defaultvalue": 0,
    "displayName": "Coop4 - Relentless Bouncers"
  },
  {
    "name": "m4p53_m4p53",
    "defaultvalue": 0,
    "displayName": "Coop4 - Relentless Chasers"
  },
  {
    "name": "m4p54_m4p54",
    "defaultvalue": 0,
    "displayName": "Coop4 - Relentless Barrier Chase"
  },
  {
    "name": "m4p55_m4p55",
    "defaultvalue": 0,
    "displayName": "Coop4 - Relentless Three's A Crowd"
  },
  {
    "name": "m4p56_m4p56",
    "defaultvalue": 0,
    "displayName": "Coop4 - Relentless Tactical Village"
  },
  {
    "name": "m4p57_m4p57",
    "defaultvalue": 0,
    "displayName": "Coop4 - Relentless They Grow On You"
  },
  {
    "name": "m4p58_m4p58",
    "defaultvalue": 0,
    "displayName": "Coop4 - Relentless Bouncing Strategic"
  },
  {
    "name": "m4p59_m4p59",
    "defaultvalue": 0,
    "displayName": "Coop4 - Relentless Trails In Darkness"
  },
  {
    "name": "m4p60_m4p60",
    "defaultvalue": 0,
    "displayName": "Coop4 - Relentless In The Deep End"
  },
  {
    "name": "m4p61_m4p61",
    "defaultvalue": 0,
    "displayName": "Coop4 - Relentless Mass Harassment"
  },
  {
    "name": "m4p62_m4p62",
    "defaultvalue": 0,
    "displayName": "Coop4 - Relentless Zomballs 2"
  },
  {
    "name": "m4p63_m4p63",
    "defaultvalue": 0,
    "displayName": "Coop4 - Relentless A Bullet Bashing"
  },
  {
    "name": "m4p64_m4p64",
    "defaultvalue": 0,
    "displayName": "Coop4 - Relentless Growing Pains"
  },
  {
    "name": "m4p65_m4p65",
    "defaultvalue": 0,
    "displayName": "Coop4 - Relentless Watch Your Six"
  },
  {
    "name": "m4p66_m4p66",
    "defaultvalue": 0,
    "displayName": "Coop4 - Relentless What Grows Up"
  },
  {
    "name": "m4p67_m4p67",
    "defaultvalue": 0,
    "displayName": "Coop4 - Relentless Triple Threat"
  },
  {
    "name": "m4p68_m4p68",
    "defaultvalue": 0,
    "displayName": "Coop4 - Relentless Variety Hour"
  },
  {
    "name": "m4p69_m4p69",
    "defaultvalue": 0,
    "displayName": "Coop4 - Relentless Watch Your Moves"
  },
  {
    "name": "m4p70_m4p70",
    "defaultvalue": 0,
    "displayName": "Coop4 - Relentless All Of The Things"
  },
  {
    "name": "m4p71_m4p71",
    "defaultvalue": 0,
    "displayName": "Coop4 - Relentless Reaction Extreme"
  },
  {
    "name": "m4p72_m4p72",
    "defaultvalue": 0,
    "displayName": "Coop4 - Relentless Defender"
  },
  {
    "name": "m4p73_m4p73",
    "defaultvalue": 0,
    "displayName": "Coop4 - Relentless Mega Barrier"
  },
  {
    "name": "m4p74_m4p74",
    "defaultvalue": 0,
    "displayName": "Coop4 - Relentless Mine Those Turrets"
  },
  {
    "name": "m4p75_m4p75",
    "defaultvalue": 0,
    "displayName": "Coop4 - Relentless Super Sneaky"
  },
  {
    "name": "m4p76_m4p76",
    "defaultvalue": 0,
    "displayName": "Coop4 - Relentless Quick Hecticism"
  },
  {
    "name": "m4p77_m4p77",
    "defaultvalue": 0,
    "displayName": "Coop4 - Relentless Spice Of Life"
  },
  {
    "name": "m4p78_m4p78",
    "defaultvalue": 0,
    "displayName": "Coop4 - Relentless Bouncer Bedlam"
  },
  {
    "name": "m4p79_m4p79",
    "defaultvalue": 0,
    "displayName": "Coop4 - Relentless Turbo Minefield"
  },
  {
    "name": "m4p80_m4p80",
    "defaultvalue": 0,
    "displayName": "Coop4 - Relentless Zomballs Extreme"
  },
  {
    "name": "m4p81_m4p81",
    "defaultvalue": 0,
    "displayName": "Coop4 - Relentless Bounce Core"
  },
  {
    "name": "m4p82_m4p82",
    "defaultvalue": 0,
    "displayName": "Coop4 - Relentless Growing Mental"
  },
  {
    "name": "m4p83_m4p83",
    "defaultvalue": 0,
    "displayName": "Coop4 - Relentless Hardcore Classic"
  },
  {
    "name": "m4p84_m4p84",
    "defaultvalue": 0,
    "displayName": "Coop4 - Relentless Quick As You Can"
  },
  {
    "name": "m4p85_m4p85",
    "defaultvalue": 0,
    "displayName": "Coop4 - Relentless Hardcore 1's And 2's"
  },
  {
    "name": "m4p86_m4p86",
    "defaultvalue": 0,
    "displayName": "Coop4 - Relentless Chase Down"
  },
  {
    "name": "m4p87_m4p87",
    "defaultvalue": 0,
    "displayName": "Coop4 - Relentless Triple Core"
  },
  {
    "name": "m4p88_m4p88",
    "defaultvalue": 0,
    "displayName": "Coop4 - Relentless Gun Run"
  },
  {
    "name": "m4p89_m4p89",
    "defaultvalue": 0,
    "displayName": "Coop4 - Relentless Trail Blazer"
  },
  {
    "name": "m4p90_m4p90",
    "defaultvalue": 0,
    "displayName": "Coop4 - Relentless Stupid"
  },
  {
    "name": "m4p91_m4p91",
    "defaultvalue": 0,
    "displayName": "Coop4 - Relentless Bouncing Ridiculous"
  },
  {
    "name": "m4p92_m4p92",
    "defaultvalue": 0,
    "displayName": "Coop4 - Relentless All The Twos"
  },
  {
    "name": "m4p93_m4p93",
    "defaultvalue": 0,
    "displayName": "Coop4 - Relentless Barrier Mayhem"
  },
  {
    "name": "m4p94_m4p94",
    "defaultvalue": 0,
    "displayName": "Coop4 - Relentless All The Threes"
  },
  {
    "name": "m4p95_m4p95",
    "defaultvalue": 0,
    "displayName": "Coop4 - Relentless Speed Modification"
  },
  {
    "name": "m4p96_m4p96",
    "defaultvalue": 0,
    "displayName": "Coop4 - Relentless Super Sneaky Plus"
  },
  {
    "name": "m4p97_m4p97",
    "defaultvalue": 0,
    "displayName": "Coop4 - Relentless Intense Closure"
  },
  {
    "name": "m4p98_m4p98",
    "defaultvalue": 0,
    "displayName": "Coop4 - Relentless Tripler Blanket"
  },
  {
    "name": "m4p99_m4p99",
    "defaultvalue": 0,
    "displayName": "Coop4 - Relentless Bullet Hell"
  },
  {
    "name": "m4p100_m4p100",
    "defaultvalue": 0,
    "displayName": "Coop4 - Relentless Utter Mayhem"
  },
  {
    "name": "sd1_sd1",
    "defaultvalue": 0,
    "displayName": "Casual Decathlon"
  },
  {
    "name": "sd2_sd2",
    "defaultvalue": 0,
    "displayName": "Classic Decathlon"
  },
  {
    "name": "sd3_sd3",
    "defaultvalue": 0,
    "displayName": "Hectic Decathlon"
  },
  {
    "name": "sd4_sd4",
    "defaultvalue": 0,
    "displayName": "Hardcore Decathlon"
  },
  {
    "name": "sd5_sd5",
    "defaultvalue": 0,
    "displayName": "Ninja Pro Decathlon"
  },
  {
    "name": "sd6_sd6",
    "defaultvalue": 0,
    "displayName": "Relentless Casual Decathlon"
  },
  {
    "name": "sd7_sd7",
    "defaultvalue": 0,
    "displayName": "Relentless Classic Decathlon"
  },
  {
    "name": "sd8_sd8",
    "defaultvalue": 0,
    "displayName": "Relentless Hectic Decathlon"
  },
  {
    "name": "sd9_sd9",
    "defaultvalue": 0,
    "displayName": "Relentless Hardcore Decathlon"
  },
  {
    "name": "sd10_sd10",
    "defaultvalue": 0,
    "displayName": "Relentless Ninja Pro Decathlon"
  },
  {
    "name": "md1_md1",
    "defaultvalue": 0,
    "displayName": "Multi - Casual Decathlon"
  },
  {
    "name": "md2_md2",
    "defaultvalue": 0,
    "displayName": "Multi - Classic Decathlon"
  },
  {
    "name": "md3_md3",
    "defaultvalue": 0,
    "displayName": "Multi - Hectic Decathlon"
  },
  {
    "name": "md4_md4",
    "defaultvalue": 0,
    "displayName": "Multi - Hardcore Decathlon"
  },
  {
    "name": "md5_md5",
    "defaultvalue": 0,
    "displayName": "Multi - Ninja Pro Decathlon"
  },
  {
    "name": "md6_md6",
    "defaultvalue": 0,
    "displayName": "Multi - Relentless Casual Decathlon"
  },
  {
    "name": "md7_md7",
    "defaultvalue": 0,
    "displayName": "Multi - Relentless Classic Decathlon"
  },
  {
    "name": "md8_md8",
    "defaultvalue": 0,
    "displayName": "Multi - Relentless Hectic Decathlon"
  },
  {
    "name": "md9_md9",
    "defaultvalue": 0,
    "displayName": "Multi - Relentless Hardcore Decathlon"
  },
  {
    "name": "md10_md10",
    "defaultvalue": 0,
    "displayName": "Multi - Relentless Ninja Pro Decathlon"
  },
  {
    "name": "m2pd1_m2pd1",
    "defaultvalue": 0,
    "displayName": "Coop2 - Casual Decathlon"
  },
  {
    "name": "m2pd2_m2pd2",
    "defaultvalue": 0,
    "displayName": "Coop2 - Classic Decathlon"
  },
  {
    "name": "m2pd3_m2pd3",
    "defaultvalue": 0,
    "displayName": "Coop2 - Hectic Decathlon"
  },
  {
    "name": "m2pd4_m2pd4",
    "defaultvalue": 0,
    "displayName": "Coop2 - Hardcore Decathlon"
  },
  {
    "name": "m2pd5_m2pd5",
    "defaultvalue": 0,
    "displayName": "Coop2 - Ninja Pro Decathlon"
  },
  {
    "name": "m2pd6_m2pd6",
    "defaultvalue": 0,
    "displayName": "Coop2 - Relentless Casual Decathlon"
  },
  {
    "name": "m2pd7_m2pd7",
    "defaultvalue": 0,
    "displayName": "Coop2 - Relentless Classic Decathlon"
  },
  {
    "name": "m2pd8_m2pd8",
    "defaultvalue": 0,
    "displayName": "Coop2 - Relentless Hectic Decathlon"
  },
  {
    "name": "m2pd9_m2pd9",
    "defaultvalue": 0,
    "displayName": "Coop2 - Relentless Hardcore Decathlon"
  },
  {
    "name": "m2pd10_m2pd10",
    "defaultvalue": 0,
    "displayName": "Coop2 - Relentless Ninja Pro Decathlon"
  },
  {
    "name": "m4pd1_m4pd1",
    "defaultvalue": 0,
    "displayName": "Coop4 - Casual Decathlon"
  },
  {
    "name": "m4pd2_m4pd2",
    "defaultvalue": 0,
    "displayName": "Coop4 - Classic Decathlon"
  },
  {
    "name": "m4pd3_m4pd3",
    "defaultvalue": 0,
    "displayName": "Coop4 - Hectic Decathlon"
  },
  {
    "name": "m4pd4_m4pd4",
    "defaultvalue": 0,
    "displayName": "Coop4 - Hardcore Decathlon"
  },
  {
    "name": "m4pd5_m4pd5",
    "defaultvalue": 0,
    "displayName": "Coop4 - Ninja Pro Decathlon"
  },
  {
    "name": "m4pd6_m4pd6",
    "defaultvalue": 0,
    "displayName": "Coop4 - Relentless Casual Decathlon"
  },
  {
    "name": "m4pd7_m4pd7",
    "defaultvalue": 0,
    "displayName": "Coop4 - Relentless Classic Decathlon"
  },
  {
    "name": "m4pd8_m4pd8",
    "defaultvalue": 0,
    "displayName": "Coop4 - Relentless Hectic Decathlon"
  },
  {
    "name": "m4pd9_m4pd9",
    "defaultvalue": 0,
    "displayName": "Coop4 - Relentless Hardcore Decathlon"
  },
  {
    "name": "m4pd10_m4pd10",
    "defaultvalue": 0,
    "displayName": "Coop4 - Relentless Ninja Pro Decathlon"
  },
  {
    "name": "s18_s18",
    "defaultvalue": 0,
    "displayName": "Variety Hour"
  },
  {
    "name": "s19_s19",
    "defaultvalue": 0,
    "displayName": "Watch Your Moves"
  },
  {
    "name": "s22_s22",
    "defaultvalue": 0,
    "displayName": "Defender"
  },
  {
    "name": "s23_s23",
    "defaultvalue": 0,
    "displayName": "Mega Barrier"
  },
  {
    "name": "t1_t1",
    "defaultvalue": 0,
    "displayName": ""
  },
  {
    "name": "t2_t2",
    "defaultvalue": 0,
    "displayName": ""
  },
  {
    "name": "t3_t3",
    "defaultvalue": 0,
    "displayName": ""
  },
  {
    "name": "t4_t4",
    "defaultvalue": 0,
    "displayName": ""
  },
  {
    "name": "t5_t5",
    "defaultvalue": 0,
    "displayName": ""
  },
  {
    "name": "t6_t6",
    "defaultvalue": 0,
    "displayName": ""
  },
  {
    "name": "t7_t7",
    "defaultvalue": 0,
    "displayName": ""
  },
  {
    "name": "t8_t8",
    "defaultvalue": 0,
    "displayName": ""
  },
  {
    "name": "t9_t9",
    "defaultvalue": 0,
    "displayName": ""
  },
  {
    "name": "t10_t10",
    "defaultvalue": 0,
    "displayName": ""
  },
  {
    "name": "t11_t11",
    "defaultvalue": 0,
    "displayName": ""
  },
  {
    "name": "t12_t12",
    "defaultvalue": 0,
    "displayName": ""
  },
  {
    "name": "t13_t13",
    "defaultvalue": 0,
    "displayName": ""
  },
  {
    "name": "t14_t14",
    "defaultvalue": 0,
    "displayName": ""
  },
  {
    "name": "t15_t15",
    "defaultvalue": 0,
    "displayName": ""
  },
  {
    "name": "t16_t16",
    "defaultvalue": 0,
    "displayName": ""
  },
  {
    "name": "t17_t17",
    "defaultvalue": 0,
    "displayName": ""
  },
  {
    "name": "t18_t18",
    "defaultvalue": 0,
    "displayName": ""
  },
  {
    "name": "t19_t19",
    "defaultvalue": 0,
    "displayName": ""
  },
  {
    "name": "t20_t20",
    "defaultvalue": 0,
    "displayName": ""
  },
  {
    "name": "t21_t21",
    "defaultvalue": 0,
    "displayName": ""
  },
  {
    "name": "t22_t22",
    "defaultvalue": 0,
    "displayName": ""
  },
  {
    "name": "t23_t23",
    "defaultvalue": 0,
    "displayName": ""
  },
  {
    "name": "t24_t24",
    "defaultvalue": 0,
    "displayName": ""
  },
  {
    "name": "t25_t25",
    "defaultvalue": 0,
    "displayName": ""
  },
  {
    "name": "t26_t26",
    "defaultvalue": 0,
    "displayName": ""
  },
  {
    "name": "t27_t27",
    "defaultvalue": 0,
    "displayName": ""
  },
  {
    "name": "t28_t28",
    "defaultvalue": 0,
    "displayName": ""
  },
  {
    "name": "t29_t29",
    "defaultvalue": 0,
    "displayName": ""
  },
  {
    "name": "t30_t30",
    "defaultvalue": 0,
    "displayName": ""
  },
  {
    "name": "t31_t31",
    "defaultvalue": 0,
    "displayName": ""
  },
  {
    "name": "t32_t32",
    "defaultvalue": 0,
    "displayName": ""
  },
  {
    "name": "t33_t33",
    "defaultvalue": 0,
    "displayName": ""
  },
  {
    "name": "t34_t34",
    "defaultvalue": 0,
    "displayName": ""
  },
  {
    "name": "t35_t35",
    "defaultvalue": 0,
    "displayName": ""
  },
  {
    "name": "t36_t36",
    "defaultvalue": 0,
    "displayName": ""
  },
  {
    "name": "t37_t37",
    "defaultvalue": 0,
    "displayName": ""
  },
  {
    "name": "t38_t38",
    "defaultvalue": 0,
    "displayName": ""
  },
  {
    "name": "t39_t39",
    "defaultvalue": 0,
    "displayName": ""
  },
  {
    "name": "t40_t40",
    "defaultvalue": 0,
    "displayName": ""
  },
  {
    "name": "t41_t41",
    "defaultvalue": 0,
    "displayName": ""
  },
  {
    "name": "t42_t42",
    "defaultvalue": 0,
    "displayName": ""
  },
  {
    "name": "t43_t43",
    "defaultvalue": 0,
    "displayName": ""
  },
  {
    "name": "t44_t44",
    "defaultvalue": 0,
    "displayName": ""
  },
  {
    "name": "t45_t45",
    "defaultvalue": 0,
    "displayName": ""
  },
  {
    "name": "t46_t46",
    "defaultvalue": 0,
    "displayName": ""
  },
  {
    "name": "t47_t47",
    "defaultvalue": 0,
    "displayName": ""
  },
  {
    "name": "t48_t48",
    "defaultvalue": 0,
    "displayName": ""
  },
  {
    "name": "t49_t49",
    "defaultvalue": 0,
    "displayName": ""
  },
  {
    "name": "t50_t50",
    "defaultvalue": 0,
    "displayName": ""
  },
  {
    "name": "t51_t51",
    "defaultvalue": 0,
    "displayName": ""
  },
  {
    "name": "t52_t52",
    "defaultvalue": 0,
    "displayName": ""
  },
  {
    "name": "t53_t53",
    "defaultvalue": 0,
    "displayName": ""
  },
  {
    "name": "t54_t54",
    "defaultvalue": 0,
    "displayName": ""
  },
  {
    "name": "t55_t55",
    "defaultvalue": 0,
    "displayName": ""
  },
  {
    "name": "t56_t56",
    "defaultvalue": 0,
    "displayName": ""
  },
  {
    "name": "t57_t57",
    "defaultvalue": 0,
    "displayName": ""
  },
  {
    "name": "t58_t58",
    "defaultvalue": 0,
    "displayName": ""
  },
  {
    "name": "t59_t59",
    "defaultvalue": 0,
    "displayName": ""
  },
  {
    "name": "t60_t60",
    "defaultvalue": 0,
    "displayName": ""
  },
  {
    "name": "t61_t61",
    "defaultvalue": 0,
    "displayName": ""
  },
  {
    "name": "t62_t62",
    "defaultvalue": 0,
    "displayName": ""
  },
  {
    "name": "t63_t63",
    "defaultvalue": 0,
    "displayName": ""
  },
  {
    "name": "t64_t64",
    "defaultvalue": 0,
    "displayName": ""
  },
  {
    "name": "t65_t65",
    "defaultvalue": 0,
    "displayName": ""
  },
  {
    "name": "t66_t66",
    "defaultvalue": 0,
    "displayName": ""
  },
  {
    "name": "t67_t67",
    "defaultvalue": 0,
    "displayName": ""
  },
  {
    "name": "t68_t68",
    "defaultvalue": 0,
    "displayName": ""
  },
  {
    "name": "t69_t69",
    "defaultvalue": 0,
    "displayName": ""
  },
  {
    "name": "t70_t70",
    "defaultvalue": 0,
    "displayName": ""
  },
  {
    "name": "t71_t71",
    "defaultvalue": 0,
    "displayName": ""
  },
  {
    "name": "t72_t72",
    "defaultvalue": 0,
    "displayName": ""
  },
  {
    "name": "t73_t73",
    "defaultvalue": 0,
    "displayName": ""
  },
  {
    "name": "t74_t74",
    "defaultvalue": 0,
    "displayName": ""
  },
  {
    "name": "t75_t75",
    "defaultvalue": 0,
    "displayName": ""
  },
  {
    "name": "t76_t76",
    "defaultvalue": 0,
    "displayName": ""
  },
  {
    "name": "t77_t77",
    "defaultvalue": 0,
    "displayName": ""
  },
  {
    "name": "t78_t78",
    "defaultvalue": 0,
    "displayName": ""
  },
  {
    "name": "t79_t79",
    "defaultvalue": 0,
    "displayName": ""
  },
  {
    "name": "t80_t80",
    "defaultvalue": 0,
    "displayName": ""
  },
  {
    "name": "t81_t81",
    "defaultvalue": 0,
    "displayName": ""
  },
  {
    "name": "t82_t82",
    "defaultvalue": 0,
    "displayName": ""
  },
  {
    "name": "t83_t83",
    "defaultvalue": 0,
    "displayName": ""
  },
  {
    "name": "t84_t84",
    "defaultvalue": 0,
    "displayName": ""
  },
  {
    "name": "t85_t85",
    "defaultvalue": 0,
    "displayName": ""
  },
  {
    "name": "t86_t86",
    "defaultvalue": 0,
    "displayName": ""
  },
  {
    "name": "t87_t87",
    "defaultvalue": 0,
    "displayName": ""
  },
  {
    "name": "t88_t88",
    "defaultvalue": 0,
    "displayName": ""
  },
  {
    "name": "t89_t89",
    "defaultvalue": 0,
    "displayName": ""
  },
  {
    "name": "t90_t90",
    "defaultvalue": 0,
    "displayName": ""
  },
  {
    "name": "t91_t91",
    "defaultvalue": 0,
    "displayName": ""
  },
  {
    "name": "t92_t92",
    "defaultvalue": 0,
    "displayName": ""
  },
  {
    "name": "t93_t93",
    "defaultvalue": 0,
    "displayName": ""
  },
  {
    "name": "t94_t94",
    "defaultvalue": 0,
    "displayName": ""
  },
  {
    "name": "t95_t95",
    "defaultvalue": 0,
    "displayName": ""
  },
  {
    "name": "t96_t96",
    "defaultvalue": 0,
    "displayName": ""
  },
  {
    "name": "t97_t97",
    "defaultvalue": 0,
    "displayName": ""
  },
  {
    "name": "t98_t98",
    "defaultvalue": 0,
    "displayName": ""
  },
  {
    "name": "t99_t99",
    "defaultvalue": 0,
    "displayName": ""
  },
  {
    "name": "t100_t100",
    "defaultvalue": 0,
    "displayName": ""
  },
  {
    "name": "tm1_tm1",
    "defaultvalue": 0,
    "displayName": ""
  },
  {
    "name": "tm2_tm2",
    "defaultvalue": 0,
    "displayName": ""
  },
  {
    "name": "tm3_tm3",
    "defaultvalue": 0,
    "displayName": ""
  },
  {
    "name": "tm4_tm4",
    "defaultvalue": 0,
    "displayName": ""
  },
  {
    "name": "tm5_tm5",
    "defaultvalue": 0,
    "displayName": ""
  },
  {
    "name": "tm6_tm6",
    "defaultvalue": 0,
    "displayName": ""
  },
  {
    "name": "tm7_tm7",
    "defaultvalue": 0,
    "displayName": ""
  },
  {
    "name": "tm8_tm8",
    "defaultvalue": 0,
    "displayName": ""
  },
  {
    "name": "tm9_tm9",
    "defaultvalue": 0,
    "displayName": ""
  },
  {
    "name": "tm10_tm10",
    "defaultvalue": 0,
    "displayName": ""
  },
  {
    "name": "tm11_tm11",
    "defaultvalue": 0,
    "displayName": ""
  },
  {
    "name": "tm12_tm12",
    "defaultvalue": 0,
    "displayName": ""
  },
  {
    "name": "tm13_tm13",
    "defaultvalue": 0,
    "displayName": ""
  },
  {
    "name": "tm14_tm14",
    "defaultvalue": 0,
    "displayName": ""
  },
  {
    "name": "tm15_tm15",
    "defaultvalue": 0,
    "displayName": ""
  },
  {
    "name": "tm16_tm16",
    "defaultvalue": 0,
    "displayName": ""
  },
  {
    "name": "tm17_tm17",
    "defaultvalue": 0,
    "displayName": ""
  },
  {
    "name": "tm18_tm18",
    "defaultvalue": 0,
    "displayName": ""
  },
  {
    "name": "tm19_tm19",
    "defaultvalue": 0,
    "displayName": ""
  },
  {
    "name": "tm20_tm20",
    "defaultvalue": 0,
    "displayName": ""
  },
  {
    "name": "tm21_tm21",
    "defaultvalue": 0,
    "displayName": ""
  },
  {
    "name": "tm22_tm22",
    "defaultvalue": 0,
    "displayName": ""
  },
  {
    "name": "tm23_tm23",
    "defaultvalue": 0,
    "displayName": ""
  },
  {
    "name": "tm24_tm24",
    "defaultvalue": 0,
    "displayName": ""
  },
  {
    "name": "tm25_tm25",
    "defaultvalue": 0,
    "displayName": ""
  },
  {
    "name": "tm26_tm26",
    "defaultvalue": 0,
    "displayName": ""
  },
  {
    "name": "tm27_tm27",
    "defaultvalue": 0,
    "displayName": ""
  },
  {
    "name": "tm28_tm28",
    "defaultvalue": 0,
    "displayName": ""
  },
  {
    "name": "tm29_tm29",
    "defaultvalue": 0,
    "displayName": ""
  },
  {
    "name": "tm30_tm30",
    "defaultvalue": 0,
    "displayName": ""
  },
  {
    "name": "tm31_tm31",
    "defaultvalue": 0,
    "displayName": ""
  },
  {
    "name": "tm32_tm32",
    "defaultvalue": 0,
    "displayName": ""
  },
  {
    "name": "tm33_tm33",
    "defaultvalue": 0,
    "displayName": ""
  },
  {
    "name": "tm34_tm34",
    "defaultvalue": 0,
    "displayName": ""
  },
  {
    "name": "tm35_tm35",
    "defaultvalue": 0,
    "displayName": ""
  },
  {
    "name": "tm36_tm36",
    "defaultvalue": 0,
    "displayName": ""
  },
  {
    "name": "tm37_tm37",
    "defaultvalue": 0,
    "displayName": ""
  },
  {
    "name": "tm38_tm38",
    "defaultvalue": 0,
    "displayName": ""
  },
  {
    "name": "tm39_tm39",
    "defaultvalue": 0,
    "displayName": ""
  },
  {
    "name": "tm40_tm40",
    "defaultvalue": 0,
    "displayName": ""
  },
  {
    "name": "tm41_tm41",
    "defaultvalue": 0,
    "displayName": ""
  },
  {
    "name": "tm42_tm42",
    "defaultvalue": 0,
    "displayName": ""
  },
  {
    "name": "tm43_tm43",
    "defaultvalue": 0,
    "displayName": ""
  },
  {
    "name": "tm44_tm44",
    "defaultvalue": 0,
    "displayName": ""
  },
  {
    "name": "tm45_tm45",
    "defaultvalue": 0,
    "displayName": ""
  },
  {
    "name": "tm46_tm46",
    "defaultvalue": 0,
    "displayName": ""
  },
  {
    "name": "tm47_tm47",
    "defaultvalue": 0,
    "displayName": ""
  },
  {
    "name": "tm48_tm48",
    "defaultvalue": 0,
    "displayName": ""
  },
  {
    "name": "tm49_tm49",
    "defaultvalue": 0,
    "displayName": ""
  },
  {
    "name": "tm50_tm50",
    "defaultvalue": 0,
    "displayName": ""
  },
  {
    "name": "tm51_tm51",
    "defaultvalue": 0,
    "displayName": ""
  },
  {
    "name": "tm52_tm52",
    "defaultvalue": 0,
    "displayName": ""
  },
  {
    "name": "tm53_tm53",
    "defaultvalue": 0,
    "displayName": ""
  },
  {
    "name": "tm54_tm54",
    "defaultvalue": 0,
    "displayName": ""
  },
  {
    "name": "tm55_tm55",
    "defaultvalue": 0,
    "displayName": ""
  },
  {
    "name": "tm56_tm56",
    "defaultvalue": 0,
    "displayName": ""
  },
  {
    "name": "tm57_tm57",
    "defaultvalue": 0,
    "displayName": ""
  },
  {
    "name": "tm58_tm58",
    "defaultvalue": 0,
    "displayName": ""
  },
  {
    "name": "tm59_tm59",
    "defaultvalue": 0,
    "displayName": ""
  },
  {
    "name": "tm60_tm60",
    "defaultvalue": 0,
    "displayName": ""
  },
  {
    "name": "tm61_tm61",
    "defaultvalue": 0,
    "displayName": ""
  },
  {
    "name": "tm62_tm62",
    "defaultvalue": 0,
    "displayName": ""
  },
  {
    "name": "tm63_tm63",
    "defaultvalue": 0,
    "displayName": ""
  },
  {
    "name": "tm64_tm64",
    "defaultvalue": 0,
    "displayName": ""
  },
  {
    "name": "tm65_tm65",
    "defaultvalue": 0,
    "displayName": ""
  },
  {
    "name": "tm66_tm66",
    "defaultvalue": 0,
    "displayName": ""
  },
  {
    "name": "tm67_tm67",
    "defaultvalue": 0,
    "displayName": ""
  },
  {
    "name": "tm68_tm68",
    "defaultvalue": 0,
    "displayName": ""
  },
  {
    "name": "tm69_tm69",
    "defaultvalue": 0,
    "displayName": ""
  },
  {
    "name": "tm70_tm70",
    "defaultvalue": 0,
    "displayName": ""
  },
  {
    "name": "tm71_tm71",
    "defaultvalue": 0,
    "displayName": ""
  },
  {
    "name": "tm72_tm72",
    "defaultvalue": 0,
    "displayName": ""
  },
  {
    "name": "tm73_tm73",
    "defaultvalue": 0,
    "displayName": ""
  },
  {
    "name": "tm74_tm74",
    "defaultvalue": 0,
    "displayName": ""
  },
  {
    "name": "tm75_tm75",
    "defaultvalue": 0,
    "displayName": ""
  },
  {
    "name": "tm76_tm76",
    "defaultvalue": 0,
    "displayName": ""
  },
  {
    "name": "tm77_tm77",
    "defaultvalue": 0,
    "displayName": ""
  },
  {
    "name": "tm78_tm78",
    "defaultvalue": 0,
    "displayName": ""
  },
  {
    "name": "tm79_tm79",
    "defaultvalue": 0,
    "displayName": ""
  },
  {
    "name": "tm80_tm80",
    "defaultvalue": 0,
    "displayName": ""
  },
  {
    "name": "tm81_tm81",
    "defaultvalue": 0,
    "displayName": ""
  },
  {
    "name": "tm82_tm82",
    "defaultvalue": 0,
    "displayName": ""
  },
  {
    "name": "tm83_tm83",
    "defaultvalue": 0,
    "displayName": ""
  },
  {
    "name": "tm84_tm84",
    "defaultvalue": 0,
    "displayName": ""
  },
  {
    "name": "tm85_tm85",
    "defaultvalue": 0,
    "displayName": ""
  },
  {
    "name": "tm86_tm86",
    "defaultvalue": 0,
    "displayName": ""
  },
  {
    "name": "tm87_tm87",
    "defaultvalue": 0,
    "displayName": ""
  },
  {
    "name": "tm88_tm88",
    "defaultvalue": 0,
    "displayName": ""
  },
  {
    "name": "tm89_tm89",
    "defaultvalue": 0,
    "displayName": ""
  },
  {
    "name": "tm90_tm90",
    "defaultvalue": 0,
    "displayName": ""
  },
  {
    "name": "tm91_tm91",
    "defaultvalue": 0,
    "displayName": ""
  },
  {
    "name": "tm92_tm92",
    "defaultvalue": 0,
    "displayName": ""
  },
  {
    "name": "tm93_tm93",
    "defaultvalue": 0,
    "displayName": ""
  },
  {
    "name": "tm94_tm94",
    "defaultvalue": 0,
    "displayName": ""
  },
  {
    "name": "tm95_tm95",
    "defaultvalue": 0,
    "displayName": ""
  },
  {
    "name": "tm96_tm96",
    "defaultvalue": 0,
    "displayName": ""
  },
  {
    "name": "tm97_tm97",
    "defaultvalue": 0,
    "displayName": ""
  },
  {
    "name": "tm98_tm98",
    "defaultvalue": 0,
    "displayName": ""
  },
  {
    "name": "tm99_tm99",
    "defaultvalue": 0,
    "displayName": ""
  },
  {
    "name": "tm100_tm100",
    "defaultvalue": 0,
    "displayName": ""
  },
  {
    "name": "t2m1_t2m1",
    "defaultvalue": 0,
    "displayName": ""
  },
  {
    "name": "t2m2_t2m2",
    "defaultvalue": 0,
    "displayName": ""
  },
  {
    "name": "t2m3_t2m3",
    "defaultvalue": 0,
    "displayName": ""
  },
  {
    "name": "t2m4_t2m4",
    "defaultvalue": 0,
    "displayName": ""
  },
  {
    "name": "t2m5_t2m5",
    "defaultvalue": 0,
    "displayName": ""
  },
  {
    "name": "t2m6_t2m6",
    "defaultvalue": 0,
    "displayName": ""
  },
  {
    "name": "t2m7_t2m7",
    "defaultvalue": 0,
    "displayName": ""
  },
  {
    "name": "t2m8_t2m8",
    "defaultvalue": 0,
    "displayName": ""
  },
  {
    "name": "t2m9_t2m9",
    "defaultvalue": 0,
    "displayName": ""
  },
  {
    "name": "t2m10_t2m10",
    "defaultvalue": 0,
    "displayName": ""
  },
  {
    "name": "t2m11_t2m11",
    "defaultvalue": 0,
    "displayName": ""
  },
  {
    "name": "t2m12_t2m12",
    "defaultvalue": 0,
    "displayName": ""
  },
  {
    "name": "t2m13_t2m13",
    "defaultvalue": 0,
    "displayName": ""
  },
  {
    "name": "t2m14_t2m14",
    "defaultvalue": 0,
    "displayName": ""
  },
  {
    "name": "t2m15_t2m15",
    "defaultvalue": 0,
    "displayName": ""
  },
  {
    "name": "t2m16_t2m16",
    "defaultvalue": 0,
    "displayName": ""
  },
  {
    "name": "t2m17_t2m17",
    "defaultvalue": 0,
    "displayName": ""
  },
  {
    "name": "t2m18_t2m18",
    "defaultvalue": 0,
    "displayName": ""
  },
  {
    "name": "t2m19_t2m19",
    "defaultvalue": 0,
    "displayName": ""
  },
  {
    "name": "t2m20_t2m20",
    "defaultvalue": 0,
    "displayName": ""
  },
  {
    "name": "t2m21_t2m21",
    "defaultvalue": 0,
    "displayName": ""
  },
  {
    "name": "t2m22_t2m22",
    "defaultvalue": 0,
    "displayName": ""
  },
  {
    "name": "t2m23_t2m23",
    "defaultvalue": 0,
    "displayName": ""
  },
  {
    "name": "t2m24_t2m24",
    "defaultvalue": 0,
    "displayName": ""
  },
  {
    "name": "t2m25_t2m25",
    "defaultvalue": 0,
    "displayName": ""
  },
  {
    "name": "t2m26_t2m26",
    "defaultvalue": 0,
    "displayName": ""
  },
  {
    "name": "t2m27_t2m27",
    "defaultvalue": 0,
    "displayName": ""
  },
  {
    "name": "t2m28_t2m28",
    "defaultvalue": 0,
    "displayName": ""
  },
  {
    "name": "t2m29_t2m29",
    "defaultvalue": 0,
    "displayName": ""
  },
  {
    "name": "t2m30_t2m30",
    "defaultvalue": 0,
    "displayName": ""
  },
  {
    "name": "t2m31_t2m31",
    "defaultvalue": 0,
    "displayName": ""
  },
  {
    "name": "t2m32_t2m32",
    "defaultvalue": 0,
    "displayName": ""
  },
  {
    "name": "t2m33_t2m33",
    "defaultvalue": 0,
    "displayName": ""
  },
  {
    "name": "t2m34_t2m34",
    "defaultvalue": 0,
    "displayName": ""
  },
  {
    "name": "t2m35_t2m35",
    "defaultvalue": 0,
    "displayName": ""
  },
  {
    "name": "t2m36_t2m36",
    "defaultvalue": 0,
    "displayName": ""
  },
  {
    "name": "t2m37_t2m37",
    "defaultvalue": 0,
    "displayName": ""
  },
  {
    "name": "t2m38_t2m38",
    "defaultvalue": 0,
    "displayName": ""
  },
  {
    "name": "t2m39_t2m39",
    "defaultvalue": 0,
    "displayName": ""
  },
  {
    "name": "t2m40_t2m40",
    "defaultvalue": 0,
    "displayName": ""
  },
  {
    "name": "t2m41_t2m41",
    "defaultvalue": 0,
    "displayName": ""
  },
  {
    "name": "t2m42_t2m42",
    "defaultvalue": 0,
    "displayName": ""
  },
  {
    "name": "t2m43_t2m43",
    "defaultvalue": 0,
    "displayName": ""
  },
  {
    "name": "t2m44_t2m44",
    "defaultvalue": 0,
    "displayName": ""
  },
  {
    "name": "t2m45_t2m45",
    "defaultvalue": 0,
    "displayName": ""
  },
  {
    "name": "t2m46_t2m46",
    "defaultvalue": 0,
    "displayName": ""
  },
  {
    "name": "t2m47_t2m47",
    "defaultvalue": 0,
    "displayName": ""
  },
  {
    "name": "t2m48_t2m48",
    "defaultvalue": 0,
    "displayName": ""
  },
  {
    "name": "t2m49_t2m49",
    "defaultvalue": 0,
    "displayName": ""
  },
  {
    "name": "t2m50_t2m50",
    "defaultvalue": 0,
    "displayName": ""
  },
  {
    "name": "t2m51_t2m51",
    "defaultvalue": 0,
    "displayName": ""
  },
  {
    "name": "t2m52_t2m52",
    "defaultvalue": 0,
    "displayName": ""
  },
  {
    "name": "t2m53_t2m53",
    "defaultvalue": 0,
    "displayName": ""
  },
  {
    "name": "t2m54_t2m54",
    "defaultvalue": 0,
    "displayName": ""
  },
  {
    "name": "t2m55_t2m55",
    "defaultvalue": 0,
    "displayName": ""
  },
  {
    "name": "t2m56_t2m56",
    "defaultvalue": 0,
    "displayName": ""
  },
  {
    "name": "t2m57_t2m57",
    "defaultvalue": 0,
    "displayName": ""
  },
  {
    "name": "t2m58_t2m58",
    "defaultvalue": 0,
    "displayName": ""
  },
  {
    "name": "t2m59_t2m59",
    "defaultvalue": 0,
    "displayName": ""
  },
  {
    "name": "t2m60_t2m60",
    "defaultvalue": 0,
    "displayName": ""
  },
  {
    "name": "t2m61_t2m61",
    "defaultvalue": 0,
    "displayName": ""
  },
  {
    "name": "t2m62_t2m62",
    "defaultvalue": 0,
    "displayName": ""
  },
  {
    "name": "t2m63_t2m63",
    "defaultvalue": 0,
    "displayName": ""
  },
  {
    "name": "t2m64_t2m64",
    "defaultvalue": 0,
    "displayName": ""
  },
  {
    "name": "t2m65_t2m65",
    "defaultvalue": 0,
    "displayName": ""
  },
  {
    "name": "t2m66_t2m66",
    "defaultvalue": 0,
    "displayName": ""
  },
  {
    "name": "t2m67_t2m67",
    "defaultvalue": 0,
    "displayName": ""
  },
  {
    "name": "t2m68_t2m68",
    "defaultvalue": 0,
    "displayName": ""
  },
  {
    "name": "t2m69_t2m69",
    "defaultvalue": 0,
    "displayName": ""
  },
  {
    "name": "t2m70_t2m70",
    "defaultvalue": 0,
    "displayName": ""
  },
  {
    "name": "t2m71_t2m71",
    "defaultvalue": 0,
    "displayName": ""
  },
  {
    "name": "t2m72_t2m72",
    "defaultvalue": 0,
    "displayName": ""
  },
  {
    "name": "t2m73_t2m73",
    "defaultvalue": 0,
    "displayName": ""
  },
  {
    "name": "t2m74_t2m74",
    "defaultvalue": 0,
    "displayName": ""
  },
  {
    "name": "t2m75_t2m75",
    "defaultvalue": 0,
    "displayName": ""
  },
  {
    "name": "t2m76_t2m76",
    "defaultvalue": 0,
    "displayName": ""
  },
  {
    "name": "t2m77_t2m77",
    "defaultvalue": 0,
    "displayName": ""
  },
  {
    "name": "t2m78_t2m78",
    "defaultvalue": 0,
    "displayName": ""
  },
  {
    "name": "t2m79_t2m79",
    "defaultvalue": 0,
    "displayName": ""
  },
  {
    "name": "t2m80_t2m80",
    "defaultvalue": 0,
    "displayName": ""
  },
  {
    "name": "t2m81_t2m81",
    "defaultvalue": 0,
    "displayName": ""
  },
  {
    "name": "t2m82_t2m82",
    "defaultvalue": 0,
    "displayName": ""
  },
  {
    "name": "t2m83_t2m83",
    "defaultvalue": 0,
    "displayName": ""
  },
  {
    "name": "t2m84_t2m84",
    "defaultvalue": 0,
    "displayName": ""
  },
  {
    "name": "t2m85_t2m85",
    "defaultvalue": 0,
    "displayName": ""
  },
  {
    "name": "t2m86_t2m86",
    "defaultvalue": 0,
    "displayName": ""
  },
  {
    "name": "t2m87_t2m87",
    "defaultvalue": 0,
    "displayName": ""
  },
  {
    "name": "t2m88_t2m88",
    "defaultvalue": 0,
    "displayName": ""
  },
  {
    "name": "t2m89_t2m89",
    "defaultvalue": 0,
    "displayName": ""
  },
  {
    "name": "t2m90_t2m90",
    "defaultvalue": 0,
    "displayName": ""
  },
  {
    "name": "t2m91_t2m91",
    "defaultvalue": 0,
    "displayName": ""
  },
  {
    "name": "t2m92_t2m92",
    "defaultvalue": 0,
    "displayName": ""
  },
  {
    "name": "t2m93_t2m93",
    "defaultvalue": 0,
    "displayName": ""
  },
  {
    "name": "t2m94_t2m94",
    "defaultvalue": 0,
    "displayName": ""
  },
  {
    "name": "t2m95_t2m95",
    "defaultvalue": 0,
    "displayName": ""
  },
  {
    "name": "t2m96_t2m96",
    "defaultvalue": 0,
    "displayName": ""
  },
  {
    "name": "t2m97_t2m97",
    "defaultvalue": 0,
    "displayName": ""
  },
  {
    "name": "t2m98_t2m98",
    "defaultvalue": 0,
    "displayName": ""
  },
  {
    "name": "t2m99_t2m99",
    "defaultvalue": 0,
    "displayName": ""
  },
  {
    "name": "t2m100_t2m100",
    "defaultvalue": 0,
    "displayName": ""
  },
  {
    "name": "t4m1_t4m1",
    "defaultvalue": 0,
    "displayName": ""
  },
  {
    "name": "t4m2_t4m2",
    "defaultvalue": 0,
    "displayName": ""
  },
  {
    "name": "t4m3_t4m3",
    "defaultvalue": 0,
    "displayName": ""
  },
  {
    "name": "t4m4_t4m4",
    "defaultvalue": 0,
    "displayName": ""
  },
  {
    "name": "t4m5_t4m5",
    "defaultvalue": 0,
    "displayName": ""
  },
  {
    "name": "t4m6_t4m6",
    "defaultvalue": 0,
    "displayName": ""
  },
  {
    "name": "t4m7_t4m7",
    "defaultvalue": 0,
    "displayName": ""
  },
  {
    "name": "t4m8_t4m8",
    "defaultvalue": 0,
    "displayName": ""
  },
  {
    "name": "t4m9_t4m9",
    "defaultvalue": 0,
    "displayName": ""
  },
  {
    "name": "t4m10_t4m10",
    "defaultvalue": 0,
    "displayName": ""
  },
  {
    "name": "t4m11_t4m11",
    "defaultvalue": 0,
    "displayName": ""
  },
  {
    "name": "t4m12_t4m12",
    "defaultvalue": 0,
    "displayName": ""
  },
  {
    "name": "t4m13_t4m13",
    "defaultvalue": 0,
    "displayName": ""
  },
  {
    "name": "t4m14_t4m14",
    "defaultvalue": 0,
    "displayName": ""
  },
  {
    "name": "t4m15_t4m15",
    "defaultvalue": 0,
    "displayName": ""
  },
  {
    "name": "t4m16_t4m16",
    "defaultvalue": 0,
    "displayName": ""
  },
  {
    "name": "t4m17_t4m17",
    "defaultvalue": 0,
    "displayName": ""
  },
  {
    "name": "t4m18_t4m18",
    "defaultvalue": 0,
    "displayName": ""
  },
  {
    "name": "t4m19_t4m19",
    "defaultvalue": 0,
    "displayName": ""
  },
  {
    "name": "t4m20_t4m20",
    "defaultvalue": 0,
    "displayName": ""
  },
  {
    "name": "t4m21_t4m21",
    "defaultvalue": 0,
    "displayName": ""
  },
  {
    "name": "t4m22_t4m22",
    "defaultvalue": 0,
    "displayName": ""
  },
  {
    "name": "t4m23_t4m23",
    "defaultvalue": 0,
    "displayName": ""
  },
  {
    "name": "t4m24_t4m24",
    "defaultvalue": 0,
    "displayName": ""
  },
  {
    "name": "t4m25_t4m25",
    "defaultvalue": 0,
    "displayName": ""
  },
  {
    "name": "t4m26_t4m26",
    "defaultvalue": 0,
    "displayName": ""
  },
  {
    "name": "t4m27_t4m27",
    "defaultvalue": 0,
    "displayName": ""
  },
  {
    "name": "t4m28_t4m28",
    "defaultvalue": 0,
    "displayName": ""
  },
  {
    "name": "t4m29_t4m29",
    "defaultvalue": 0,
    "displayName": ""
  },
  {
    "name": "t4m30_t4m30",
    "defaultvalue": 0,
    "displayName": ""
  },
  {
    "name": "t4m31_t4m31",
    "defaultvalue": 0,
    "displayName": ""
  },
  {
    "name": "t4m32_t4m32",
    "defaultvalue": 0,
    "displayName": ""
  },
  {
    "name": "t4m33_t4m33",
    "defaultvalue": 0,
    "displayName": ""
  },
  {
    "name": "t4m34_t4m34",
    "defaultvalue": 0,
    "displayName": ""
  },
  {
    "name": "t4m35_t4m35",
    "defaultvalue": 0,
    "displayName": ""
  },
  {
    "name": "t4m36_t4m36",
    "defaultvalue": 0,
    "displayName": ""
  },
  {
    "name": "t4m37_t4m37",
    "defaultvalue": 0,
    "displayName": ""
  },
  {
    "name": "t4m38_t4m38",
    "defaultvalue": 0,
    "displayName": ""
  },
  {
    "name": "t4m39_t4m39",
    "defaultvalue": 0,
    "displayName": ""
  },
  {
    "name": "t4m40_t4m40",
    "defaultvalue": 0,
    "displayName": ""
  },
  {
    "name": "t4m41_t4m41",
    "defaultvalue": 0,
    "displayName": ""
  },
  {
    "name": "t4m42_t4m42",
    "defaultvalue": 0,
    "displayName": ""
  },
  {
    "name": "t4m43_t4m43",
    "defaultvalue": 0,
    "displayName": ""
  },
  {
    "name": "t4m44_t4m44",
    "defaultvalue": 0,
    "displayName": ""
  },
  {
    "name": "t4m45_t4m45",
    "defaultvalue": 0,
    "displayName": ""
  },
  {
    "name": "t4m46_t4m46",
    "defaultvalue": 0,
    "displayName": ""
  },
  {
    "name": "t4m47_t4m47",
    "defaultvalue": 0,
    "displayName": ""
  },
  {
    "name": "t4m48_t4m48",
    "defaultvalue": 0,
    "displayName": ""
  },
  {
    "name": "t4m49_t4m49",
    "defaultvalue": 0,
    "displayName": ""
  },
  {
    "name": "t4m50_t4m50",
    "defaultvalue": 0,
    "displayName": ""
  },
  {
    "name": "t4m51_t4m51",
    "defaultvalue": 0,
    "displayName": ""
  },
  {
    "name": "t4m52_t4m52",
    "defaultvalue": 0,
    "displayName": ""
  },
  {
    "name": "t4m53_t4m53",
    "defaultvalue": 0,
    "displayName": ""
  },
  {
    "name": "t4m54_t4m54",
    "defaultvalue": 0,
    "displayName": ""
  },
  {
    "name": "t4m55_t4m55",
    "defaultvalue": 0,
    "displayName": ""
  },
  {
    "name": "t4m56_t4m56",
    "defaultvalue": 0,
    "displayName": ""
  },
  {
    "name": "t4m57_t4m57",
    "defaultvalue": 0,
    "displayName": ""
  },
  {
    "name": "t4m58_t4m58",
    "defaultvalue": 0,
    "displayName": ""
  },
  {
    "name": "t4m59_t4m59",
    "defaultvalue": 0,
    "displayName": ""
  },
  {
    "name": "t4m60_t4m60",
    "defaultvalue": 0,
    "displayName": ""
  },
  {
    "name": "t4m61_t4m61",
    "defaultvalue": 0,
    "displayName": ""
  },
  {
    "name": "t4m62_t4m62",
    "defaultvalue": 0,
    "displayName": ""
  },
  {
    "name": "t4m63_t4m63",
    "defaultvalue": 0,
    "displayName": ""
  },
  {
    "name": "t4m64_t4m64",
    "defaultvalue": 0,
    "displayName": ""
  },
  {
    "name": "t4m65_t4m65",
    "defaultvalue": 0,
    "displayName": ""
  },
  {
    "name": "t4m66_t4m66",
    "defaultvalue": 0,
    "displayName": ""
  },
  {
    "name": "t4m67_t4m67",
    "defaultvalue": 0,
    "displayName": ""
  },
  {
    "name": "t4m68_t4m68",
    "defaultvalue": 0,
    "displayName": ""
  },
  {
    "name": "t4m69_t4m69",
    "defaultvalue": 0,
    "displayName": ""
  },
  {
    "name": "t4m70_t4m70",
    "defaultvalue": 0,
    "displayName": ""
  },
  {
    "name": "t4m71_t4m71",
    "defaultvalue": 0,
    "displayName": ""
  },
  {
    "name": "t4m72_t4m72",
    "defaultvalue": 0,
    "displayName": ""
  },
  {
    "name": "t4m73_t4m73",
    "defaultvalue": 0,
    "displayName": ""
  },
  {
    "name": "t4m74_t4m74",
    "defaultvalue": 0,
    "displayName": ""
  },
  {
    "name": "t4m75_t4m75",
    "defaultvalue": 0,
    "displayName": ""
  },
  {
    "name": "t4m76_t4m76",
    "defaultvalue": 0,
    "displayName": ""
  },
  {
    "name": "t4m77_t4m77",
    "defaultvalue": 0,
    "displayName": ""
  },
  {
    "name": "t4m78_t4m78",
    "defaultvalue": 0,
    "displayName": ""
  },
  {
    "name": "t4m79_t4m79",
    "defaultvalue": 0,
    "displayName": ""
  },
  {
    "name": "t4m80_t4m80",
    "defaultvalue": 0,
    "displayName": ""
  },
  {
    "name": "t4m81_t4m81",
    "defaultvalue": 0,
    "displayName": ""
  },
  {
    "name": "t4m82_t4m82",
    "defaultvalue": 0,
    "displayName": ""
  },
  {
    "name": "t4m83_t4m83",
    "defaultvalue": 0,
    "displayName": ""
  },
  {
    "name": "t4m84_t4m84",
    "defaultvalue": 0,
    "displayName": ""
  },
  {
    "name": "t4m85_t4m85",
    "defaultvalue": 0,
    "displayName": ""
  },
  {
    "name": "t4m86_t4m86",
    "defaultvalue": 0,
    "displayName": ""
  },
  {
    "name": "t4m87_t4m87",
    "defaultvalue": 0,
    "displayName": ""
  },
  {
    "name": "t4m88_t4m88",
    "defaultvalue": 0,
    "displayName": ""
  },
  {
    "name": "t4m89_t4m89",
    "defaultvalue": 0,
    "displayName": ""
  },
  {
    "name": "t4m90_t4m90",
    "defaultvalue": 0,
    "displayName": ""
  },
  {
    "name": "t4m91_t4m91",
    "defaultvalue": 0,
    "displayName": ""
  },
  {
    "name": "t4m92_t4m92",
    "defaultvalue": 0,
    "displayName": ""
  },
  {
    "name": "t4m93_t4m93",
    "defaultvalue": 0,
    "displayName": ""
  },
  {
    "name": "t4m94_t4m94",
    "defaultvalue": 0,
    "displayName": ""
  },
  {
    "name": "t4m95_t4m95",
    "defaultvalue": 0,
    "displayName": ""
  },
  {
    "name": "t4m96_t4m96",
    "defaultvalue": 0,
    "displayName": ""
  },
  {
    "name": "t4m97_t4m97",
    "defaultvalue": 0,
    "displayName": ""
  },
  {
    "name": "t4m98_t4m98",
    "defaultvalue": 0,
    "displayName": ""
  },
  {
    "name": "t4m99_t4m99",
    "defaultvalue": 0,
    "displayName": ""
  },
  {
    "name": "t4m100_t4m100",
    "defaultvalue": 0,
    "displayName": ""
  },
  {
    "name": "xcs_xcs",
    "defaultvalue": 0,
    "displayName": ""
  },
  {
    "name": "xcsb_xcsb",
    "defaultvalue": 0,
    "displayName": ""
  },
  {
    "name": "xhs_xhs",
    "defaultvalue": 0,
    "displayName": ""
  },
  {
    "name": "xhsb_xhsb",
    "defaultvalue": 0,
    "displayName": ""
  },
  {
    "name": "xcm_xcm",
    "defaultvalue": 0,
    "displayName": ""
  },
  {
    "name": "xcmb_xcmb",
    "defaultvalue": 0,
    "displayName": ""
  },
  {
    "name": "xhm_xhm",
    "defaultvalue": 0,
    "displayName": ""
  },
  {
    "name": "xhmb_xhmb",
    "defaultvalue": 0,
    "displayName": ""
  },
  {
    "name": "xc2m_xc2m",
    "defaultvalue": 0,
    "displayName": ""
  },
  {
    "name": "xc2mb_xc2mb",
    "defaultvalue": 0,
    "displayName": ""
  },
  {
    "name": "xh2m_xh2m",
    "defaultvalue": 0,
    "displayName": ""
  },
  {
    "name": "xh2mb_xh2mb",
    "defaultvalue": 0,
    "displayName": ""
  },
  {
    "name": "xc4m_xc4m",
    "defaultvalue": 0,
    "displayName": ""
  },
  {
    "name": "xc4mb_xc4mb",
    "defaultvalue": 0,
    "displayName": ""
  },
  {
    "name": "xh4m_xh4m",
    "defaultvalue": 0,
    "displayName": ""
  },
  {
    "name": "xh4mb_xh4mb",
    "defaultvalue": 0,
    "displayName": ""
  },
  {
    "name": "a1_a1",
    "defaultvalue": 0,
    "displayName": ""
  },
  {
    "name": "a2_a2",
    "defaultvalue": 0,
    "displayName": ""
  },
  {
    "name": "a3_a3",
    "defaultvalue": 0,
    "displayName": ""
  },
  {
    "name": "a4_a4",
    "defaultvalue": 0,
    "displayName": ""
  },
  {
    "name": "a5_a5",
    "defaultvalue": 0,
    "displayName": ""
  },
  {
    "name": "a6_a6",
    "defaultvalue": 0,
    "displayName": ""
  },
  {
    "name": "a7_a7",
    "defaultvalue": 0,
    "displayName": ""
  },
  {
    "name": "a8_a8",
    "defaultvalue": 0,
    "displayName": ""
  },
  {
    "name": "a9_a9",
    "defaultvalue": 0,
    "displayName": ""
  },
  {
    "name": "a10_a10",
    "defaultvalue": 0,
    "displayName": ""
  },
  {
    "name": "am1_am1",
    "defaultvalue": 0,
    "displayName": ""
  },
  {
    "name": "am2_am2",
    "defaultvalue": 0,
    "displayName": ""
  },
  {
    "name": "am3_am3",
    "defaultvalue": 0,
    "displayName": ""
  },
  {
    "name": "am4_am4",
    "defaultvalue": 0,
    "displayName": ""
  },
  {
    "name": "am5_am5",
    "defaultvalue": 0,
    "displayName": ""
  },
  {
    "name": "am6_am6",
    "defaultvalue": 0,
    "displayName": ""
  },
  {
    "name": "am7_am7",
    "defaultvalue": 0,
    "displayName": ""
  },
  {
    "name": "am8_am8",
    "defaultvalue": 0,
    "displayName": ""
  },
  {
    "name": "am9_am9",
    "defaultvalue": 0,
    "displayName": ""
  },
  {
    "name": "am10_am10",
    "defaultvalue": 0,
    "displayName": ""
  },
  {
    "name": "a2m1_a2m1",
    "defaultvalue": 0,
    "displayName": ""
  },
  {
    "name": "a2m2_a2m2",
    "defaultvalue": 0,
    "displayName": ""
  },
  {
    "name": "a2m3_a2m3",
    "defaultvalue": 0,
    "displayName": ""
  },
  {
    "name": "a2m4_a2m4",
    "defaultvalue": 0,
    "displayName": ""
  },
  {
    "name": "a2m5_a2m5",
    "defaultvalue": 0,
    "displayName": ""
  },
  {
    "name": "a2m6_a2m6",
    "defaultvalue": 0,
    "displayName": ""
  },
  {
    "name": "a2m7_a2m7",
    "defaultvalue": 0,
    "displayName": ""
  },
  {
    "name": "a2m8_a2m8",
    "defaultvalue": 0,
    "displayName": ""
  },
  {
    "name": "a2m9_a2m9",
    "defaultvalue": 0,
    "displayName": ""
  },
  {
    "name": "a2m10_a2m10",
    "defaultvalue": 0,
    "displayName": ""
  },
  {
    "name": "a4m1_a4m1",
    "defaultvalue": 0,
    "displayName": ""
  },
  {
    "name": "a4m2_a4m2",
    "defaultvalue": 0,
    "displayName": ""
  },
  {
    "name": "a4m3_a4m3",
    "defaultvalue": 0,
    "displayName": ""
  },
  {
    "name": "a4m4_a4m4",
    "defaultvalue": 0,
    "displayName": ""
  },
  {
    "name": "a4m5_a4m5",
    "defaultvalue": 0,
    "displayName": ""
  },
  {
    "name": "a4m6_a4m6",
    "defaultvalue": 0,
    "displayName": ""
  },
  {
    "name": "a4m7_a4m7",
    "defaultvalue": 0,
    "displayName": ""
  },
  {
    "name": "a4m8_a4m8",
    "defaultvalue": 0,
    "displayName": ""
  },
  {
    "name": "a4m9_a4m9",
    "defaultvalue": 0,
    "displayName": ""
  },
  {
    "name": "a4m10_a4m10",
    "defaultvalue": 0,
    "displayName": ""
  }
]