[
  {
    "name": "AQUARIUS",
    "defaultvalue": 0,
    "displayName": "Players Selected Aquarius"
  },
  {
    "name": "ARIES",
    "defaultvalue": 0,
    "displayName": "Players Selected Aries"
  },
  {
    "name": "CANCER",
    "defaultvalue": 0,
    "displayName": "Players Selected Cancer"
  },
  {
    "name": "CAPRICORN",
    "defaultvalue": 0,
    "displayName": "Players Selected Capricorn"
  },
  {
    "name": "GEMINI",
    "defaultvalue": 0,
    "displayName": "Players Selected Gemini"
  },
  {
    "name": "LEO",
    "defaultvalue": 0,
    "displayName": "Players Selected Leo"
  },
  {
    "name": "LIBRA",
    "defaultvalue": 0,
    "displayName": "Players Selected Libra"
  },
  {
    "name": "PISCES",
    "defaultvalue": 0,
    "displayName": "Players Selected Pisces"
  },
  {
    "name": "SAGITTARIUS",
    "defaultvalue": 0,
    "displayName": "Players Selected Sagittarius"
  },
  {
    "name": "SCORPIO",
    "defaultvalue": 0,
    "displayName": "Players Selected Scorpio"
  },
  {
    "name": "TAURUS",
    "defaultvalue": 0,
    "displayName": "Players Selected Taurus"
  },
  {
    "name": "VIRGO",
    "defaultvalue": 0,
    "displayName": "Players Selected Virgo"
  }
]