{
  "Dlcs": {
    "959812": {
      "Name": "Garden Paws - Human Characters",
      "ImageUrl": "https://cdn.akamai.steamstatic.com/steam/apps/959812/header.jpg?t=1621265478",
      "Type": "dlc"
    },
    "959816": {
      "Name": "Garden Paws Original Soundtrack",
      "ImageUrl": "https://cdn.akamai.steamstatic.com/steam/apps/959816/header.jpg?t=1554417425",
      "Type": "dlc"
    }
  },
  "Name": "Garden Paws",
  "AppId": "840010",
  "ImageUrl": "https://cdn.akamai.steamstatic.com/steam/apps/840010/header.jpg?t=1621792407",
  "Languages": [
    "english"
  ],
  "Platforms": {
    "windows": true,
    "mac": true,
    "linux": false
  }
}